stopwatch/src/stopwatch.v
`define DIV 7'd2

module stopwatch(
	input				clk,
	input				rst_n,
	input				clear,
	input				start_stop,
	output	reg	[3:0]	hr_h,
	output	reg	[3:0]	hr_l,
	output	reg	[3:0]	min_h,
	output	reg	[3:0]	min_l,
	output	reg	[3:0]	sec_h,
	output	reg	[3:0]	sec_l
);
	reg	[6:0]	clk_cnt;
	reg			clean_trig;
	reg			state;	// 记录表状态，1为运行，0为暂停
	
	always@(posedge clk or posedge clear)begin
		if(clear)	clean_trig <= 1'b1;
		else		clean_trig <= 0;
	end
	
	always@(negedge rst_n or posedge start_stop)begin
		if(!rst_n)	state <= 0;
		else		state <= ~state;
	end

	always@(posedge clk)begin
		if((!rst_n) || clean_trig)begin	
			clk_cnt <= 0;
		end
		else begin
			if(state)begin
				if(clk_cnt == `DIV)		clk_cnt	<= 0;
				else					clk_cnt <= clk_cnt + 1'b1;
			end
		end
	end
	
	wire clk_sec	= (clk_cnt == `DIV);
	wire sec_l_rst	= (sec_l == 4'd9);
	wire sec_h_rst	= (sec_l_rst) & (sec_h == 4'd5);
	wire min_l_rst  = (sec_h_rst) & (min_l == 4'd9);
	wire min_h_rst  = (min_l_rst) & (min_h == 4'd5);
	wire hr_l_rst	= (min_h_rst) & (hr_l == 4'd9);
	wire hr_h_rst	= (hr_l_rst)  & (hr_h == 4'd5);

	always@(posedge clk)begin
		if((!rst_n) || clean_trig)begin	
			hr_h	<= 0;
            hr_l	<= 0;
            min_h	<= 0;
            min_l	<= 0;
            sec_h	<= 0;
            sec_l	<= 0;
		end
		else begin
			if(state)begin
				if(clk_sec)begin
					if		(sec_l_rst)		sec_l	<=	0;
					else					sec_l	<=	sec_l + 1'b1;

					if		(sec_h_rst)		sec_h	<=	0;
					else if (sec_l_rst)		sec_h	<=	sec_h + 1'b1;

					if		(min_l_rst)		min_l	<=	0;
					else if (sec_h_rst)		min_l	<=	min_l + 1'b1;

					if		(min_h_rst)		min_h	<=	0;
					else if (min_l_rst)		min_h	<=	min_h + 1'b1;

					if		(hr_l_rst)		hr_l	<=	0;
					else if (min_h_rst)		hr_l	<= hr_l + 1'b1;

					if		(hr_h_rst)		hr_h	<=	0;
					else if (hr_l_rst)		hr_h	<=	hr_h + 1'b1;
				end
			end
		end
	end

endmodule

stopwatch/src/stopwatch_tb.v
`timescale 1ns/1ns
module stopwatch_tb();

initial begin            
    $dumpfile("../stopwatch_tb.vcd"); 
    $dumpvars; 
end

reg			start_stop = 0;
reg			clear	= 0;
reg			rst_n	= 0;
reg			clk		= 0;
always #5	clk		= ~clk;

wire	[3:0]	hr_h;
wire	[3:0]	hr_l;
wire	[3:0]	min_h;
wire	[3:0]	min_l;
wire	[3:0]	sec_h;
wire	[3:0]	sec_l;

initial begin
	#10		rst_n		<= 1'b1;
	#203	start_stop	<= 1'b1;
	#13		start_stop	<= 0;
	#3000
	#4		clear		<= 1'b1;
	#9		clear		<= 0;
	#20000
	#3		start_stop	<= 1'b1;
	#15		start_stop	<= 0;
	#3000
	#4		clear		<= 1'b1;
	#9		clear		<= 0;
	#100
	#3		start_stop	<= 1'b1;
	#15		start_stop	<= 0;
	#100000
	$finish;
end

stopwatch dut(
	.clk				(clk),
    .rst_n				(rst_n),
    .clear				(clear),
    .start_stop			(start_stop),
    .hr_h				(hr_h),
    .hr_l				(hr_l),
    .min_h				(min_h),
    .min_l				(min_l),
    .sec_h				(sec_h),
    .sec_l				(sec_l)
);

endmodule

stopwatch/sim/stopwatch_tb.vcd
$date
	Sat Dec  2 21:44:47 2023
$end
$version
	Icarus Verilog
$end
$timescale
	1ns
$end
$scope module stopwatch_tb $end
$var wire 4 ! sec_l [3:0] $end
$var wire 4 " sec_h [3:0] $end
$var wire 4 # min_l [3:0] $end
$var wire 4 $ min_h [3:0] $end
$var wire 4 % hr_l [3:0] $end
$var wire 4 & hr_h [3:0] $end
$var reg 1 ' clear $end
$var reg 1 ( clk $end
$var reg 1 ) rst_n $end
$var reg 1 * start_stop $end
$scope module dut $end
$var wire 1 ' clear $end
$var wire 1 ( clk $end
$var wire 1 + hr_h_rst $end
$var wire 1 , hr_l_rst $end
$var wire 1 - min_h_rst $end
$var wire 1 . min_l_rst $end
$var wire 1 ) rst_n $end
$var wire 1 / sec_h_rst $end
$var wire 1 * start_stop $end
$var wire 1 0 sec_l_rst $end
$var wire 1 1 clk_sec $end
$var reg 1 2 clean_trig $end
$var reg 7 3 clk_cnt [6:0] $end
$var reg 4 4 hr_h [3:0] $end
$var reg 4 5 hr_l [3:0] $end
$var reg 4 6 min_h [3:0] $end
$var reg 4 7 min_l [3:0] $end
$var reg 4 8 sec_h [3:0] $end
$var reg 4 9 sec_l [3:0] $end
$var reg 1 : state $end
$upscope $end
$upscope $end
$enddefinitions $end
#0
$dumpvars
0:
bx 9
bx 8
bx 7
bx 6
bx 5
bx 4
bx 3
x2
x1
x0
x/
x.
x-
x,
x+
0*
0)
0(
0'
bx &
bx %
bx $
bx #
bx "
bx !
$end
#5
0/
0.
0-
0,
0+
01
b0 3
00
b0 !
b0 9
b0 "
b0 8
b0 #
b0 7
b0 $
b0 6
b0 %
b0 5
b0 &
b0 4
02
1(
#10
1)
0(
#15
1(
#20
0(
#25
1(
#30
0(
#35
1(
#40
0(
#45
1(
#50
0(
#55
1(
#60
0(
#65
1(
#70
0(
#75
1(
#80
0(
#85
1(
#90
0(
#95
1(
#100
0(
#105
1(
#110
0(
#115
1(
#120
0(
#125
1(
#130
0(
#135
1(
#140
0(
#145
1(
#150
0(
#155
1(
#160
0(
#165
1(
#170
0(
#175
1(
#180
0(
#185
1(
#190
0(
#195
1(
#200
0(
#205
1(
#210
0(
#213
1:
1*
#215
b1 3
1(
#220
0(
#225
11
b10 3
1(
#226
0*
#230
0(
#235
b1 !
b1 9
01
b0 3
1(
#240
0(
#245
b1 3
1(
#250
0(
#255
11
b10 3
1(
#260
0(
#265
01
b0 3
b10 !
b10 9
1(
#270
0(
#275
b1 3
1(
#280
0(
#285
11
b10 3
1(
#290
0(
#295
b11 !
b11 9
01
b0 3
1(
#300
0(
#305
b1 3
1(
#310
0(
#315
11
b10 3
1(
#320
0(
#325
01
b0 3
b100 !
b100 9
1(
#330
0(
#335
b1 3
1(
#340
0(
#345
11
b10 3
1(
#350
0(
#355
b101 !
b101 9
01
b0 3
1(
#360
0(
#365
b1 3
1(
#370
0(
#375
11
b10 3
1(
#380
0(
#385
01
b0 3
b110 !
b110 9
1(
#390
0(
#395
b1 3
1(
#400
0(
#405
11
b10 3
1(
#410
0(
#415
b111 !
b111 9
01
b0 3
1(
#420
0(
#425
b1 3
1(
#430
0(
#435
11
b10 3
1(
#440
0(
#445
01
b0 3
b1000 !
b1000 9
1(
#450
0(
#455
b1 3
1(
#460
0(
#465
11
b10 3
1(
#470
0(
#475
10
b1001 !
b1001 9
01
b0 3
1(
#480
0(
#485
b1 3
1(
#490
0(
#495
11
b10 3
1(
#500
0(
#505
01
b0 3
b1 "
b1 8
00
b0 !
b0 9
1(
#510
0(
#515
b1 3
1(
#520
0(
#525
11
b10 3
1(
#530
0(
#535
b1 !
b1 9
01
b0 3
1(
#540
0(
#545
b1 3
1(
#550
0(
#555
11
b10 3
1(
#560
0(
#565
01
b0 3
b10 !
b10 9
1(
#570
0(
#575
b1 3
1(
#580
0(
#585
11
b10 3
1(
#590
0(
#595
b11 !
b11 9
01
b0 3
1(
#600
0(
#605
b1 3
1(
#610
0(
#615
11
b10 3
1(
#620
0(
#625
01
b0 3
b100 !
b100 9
1(
#630
0(
#635
b1 3
1(
#640
0(
#645
11
b10 3
1(
#650
0(
#655
b101 !
b101 9
01
b0 3
1(
#660
0(
#665
b1 3
1(
#670
0(
#675
11
b10 3
1(
#680
0(
#685
01
b0 3
b110 !
b110 9
1(
#690
0(
#695
b1 3
1(
#700
0(
#705
11
b10 3
1(
#710
0(
#715
b111 !
b111 9
01
b0 3
1(
#720
0(
#725
b1 3
1(
#730
0(
#735
11
b10 3
1(
#740
0(
#745
01
b0 3
b1000 !
b1000 9
1(
#750
0(
#755
b1 3
1(
#760
0(
#765
11
b10 3
1(
#770
0(
#775
10
b1001 !
b1001 9
01
b0 3
1(
#780
0(
#785
b1 3
1(
#790
0(
#795
11
b10 3
1(
#800
0(
#805
01
b0 3
b10 "
b10 8
00
b0 !
b0 9
1(
#810
0(
#815
b1 3
1(
#820
0(
#825
11
b10 3
1(
#830
0(
#835
b1 !
b1 9
01
b0 3
1(
#840
0(
#845
b1 3
1(
#850
0(
#855
11
b10 3
1(
#860
0(
#865
01
b0 3
b10 !
b10 9
1(
#870
0(
#875
b1 3
1(
#880
0(
#885
11
b10 3
1(
#890
0(
#895
b11 !
b11 9
01
b0 3
1(
#900
0(
#905
b1 3
1(
#910
0(
#915
11
b10 3
1(
#920
0(
#925
01
b0 3
b100 !
b100 9
1(
#930
0(
#935
b1 3
1(
#940
0(
#945
11
b10 3
1(
#950
0(
#955
b101 !
b101 9
01
b0 3
1(
#960
0(
#965
b1 3
1(
#970
0(
#975
11
b10 3
1(
#980
0(
#985
01
b0 3
b110 !
b110 9
1(
#990
0(
#995
b1 3
1(
#1000
0(
#1005
11
b10 3
1(
#1010
0(
#1015
b111 !
b111 9
01
b0 3
1(
#1020
0(
#1025
b1 3
1(
#1030
0(
#1035
11
b10 3
1(
#1040
0(
#1045
01
b0 3
b1000 !
b1000 9
1(
#1050
0(
#1055
b1 3
1(
#1060
0(
#1065
11
b10 3
1(
#1070
0(
#1075
10
b1001 !
b1001 9
01
b0 3
1(
#1080
0(
#1085
b1 3
1(
#1090
0(
#1095
11
b10 3
1(
#1100
0(
#1105
01
b0 3
b11 "
b11 8
00
b0 !
b0 9
1(
#1110
0(
#1115
b1 3
1(
#1120
0(
#1125
11
b10 3
1(
#1130
0(
#1135
b1 !
b1 9
01
b0 3
1(
#1140
0(
#1145
b1 3
1(
#1150
0(
#1155
11
b10 3
1(
#1160
0(
#1165
01
b0 3
b10 !
b10 9
1(
#1170
0(
#1175
b1 3
1(
#1180
0(
#1185
11
b10 3
1(
#1190
0(
#1195
b11 !
b11 9
01
b0 3
1(
#1200
0(
#1205
b1 3
1(
#1210
0(
#1215
11
b10 3
1(
#1220
0(
#1225
01
b0 3
b100 !
b100 9
1(
#1230
0(
#1235
b1 3
1(
#1240
0(
#1245
11
b10 3
1(
#1250
0(
#1255
b101 !
b101 9
01
b0 3
1(
#1260
0(
#1265
b1 3
1(
#1270
0(
#1275
11
b10 3
1(
#1280
0(
#1285
01
b0 3
b110 !
b110 9
1(
#1290
0(
#1295
b1 3
1(
#1300
0(
#1305
11
b10 3
1(
#1310
0(
#1315
b111 !
b111 9
01
b0 3
1(
#1320
0(
#1325
b1 3
1(
#1330
0(
#1335
11
b10 3
1(
#1340
0(
#1345
01
b0 3
b1000 !
b1000 9
1(
#1350
0(
#1355
b1 3
1(
#1360
0(
#1365
11
b10 3
1(
#1370
0(
#1375
10
b1001 !
b1001 9
01
b0 3
1(
#1380
0(
#1385
b1 3
1(
#1390
0(
#1395
11
b10 3
1(
#1400
0(
#1405
01
b0 3
b100 "
b100 8
00
b0 !
b0 9
1(
#1410
0(
#1415
b1 3
1(
#1420
0(
#1425
11
b10 3
1(
#1430
0(
#1435
b1 !
b1 9
01
b0 3
1(
#1440
0(
#1445
b1 3
1(
#1450
0(
#1455
11
b10 3
1(
#1460
0(
#1465
01
b0 3
b10 !
b10 9
1(
#1470
0(
#1475
b1 3
1(
#1480
0(
#1485
11
b10 3
1(
#1490
0(
#1495
b11 !
b11 9
01
b0 3
1(
#1500
0(
#1505
b1 3
1(
#1510
0(
#1515
11
b10 3
1(
#1520
0(
#1525
01
b0 3
b100 !
b100 9
1(
#1530
0(
#1535
b1 3
1(
#1540
0(
#1545
11
b10 3
1(
#1550
0(
#1555
b101 !
b101 9
01
b0 3
1(
#1560
0(
#1565
b1 3
1(
#1570
0(
#1575
11
b10 3
1(
#1580
0(
#1585
01
b0 3
b110 !
b110 9
1(
#1590
0(
#1595
b1 3
1(
#1600
0(
#1605
11
b10 3
1(
#1610
0(
#1615
b111 !
b111 9
01
b0 3
1(
#1620
0(
#1625
b1 3
1(
#1630
0(
#1635
11
b10 3
1(
#1640
0(
#1645
01
b0 3
b1000 !
b1000 9
1(
#1650
0(
#1655
b1 3
1(
#1660
0(
#1665
11
b10 3
1(
#1670
0(
#1675
10
b1001 !
b1001 9
01
b0 3
1(
#1680
0(
#1685
b1 3
1(
#1690
0(
#1695
11
b10 3
1(
#1700
0(
#1705
01
b0 3
b101 "
b101 8
00
b0 !
b0 9
1(
#1710
0(
#1715
b1 3
1(
#1720
0(
#1725
11
b10 3
1(
#1730
0(
#1735
b1 !
b1 9
01
b0 3
1(
#1740
0(
#1745
b1 3
1(
#1750
0(
#1755
11
b10 3
1(
#1760
0(
#1765
01
b0 3
b10 !
b10 9
1(
#1770
0(
#1775
b1 3
1(
#1780
0(
#1785
11
b10 3
1(
#1790
0(
#1795
b11 !
b11 9
01
b0 3
1(
#1800
0(
#1805
b1 3
1(
#1810
0(
#1815
11
b10 3
1(
#1820
0(
#1825
01
b0 3
b100 !
b100 9
1(
#1830
0(
#1835
b1 3
1(
#1840
0(
#1845
11
b10 3
1(
#1850
0(
#1855
b101 !
b101 9
01
b0 3
1(
#1860
0(
#1865
b1 3
1(
#1870
0(
#1875
11
b10 3
1(
#1880
0(
#1885
01
b0 3
b110 !
b110 9
1(
#1890
0(
#1895
b1 3
1(
#1900
0(
#1905
11
b10 3
1(
#1910
0(
#1915
b111 !
b111 9
01
b0 3
1(
#1920
0(
#1925
b1 3
1(
#1930
0(
#1935
11
b10 3
1(
#1940
0(
#1945
01
b0 3
b1000 !
b1000 9
1(
#1950
0(
#1955
b1 3
1(
#1960
0(
#1965
11
b10 3
1(
#1970
0(
#1975
1/
10
b1001 !
b1001 9
01
b0 3
1(
#1980
0(
#1985
b1 3
1(
#1990
0(
#1995
11
b10 3
1(
#2000
0(
#2005
0/
01
b0 3
b1 #
b1 7
b0 "
b0 8
00
b0 !
b0 9
1(
#2010
0(
#2015
b1 3
1(
#2020
0(
#2025
11
b10 3
1(
#2030
0(
#2035
b1 !
b1 9
01
b0 3
1(
#2040
0(
#2045
b1 3
1(
#2050
0(
#2055
11
b10 3
1(
#2060
0(
#2065
01
b0 3
b10 !
b10 9
1(
#2070
0(
#2075
b1 3
1(
#2080
0(
#2085
11
b10 3
1(
#2090
0(
#2095
b11 !
b11 9
01
b0 3
1(
#2100
0(
#2105
b1 3
1(
#2110
0(
#2115
11
b10 3
1(
#2120
0(
#2125
01
b0 3
b100 !
b100 9
1(
#2130
0(
#2135
b1 3
1(
#2140
0(
#2145
11
b10 3
1(
#2150
0(
#2155
b101 !
b101 9
01
b0 3
1(
#2160
0(
#2165
b1 3
1(
#2170
0(
#2175
11
b10 3
1(
#2180
0(
#2185
01
b0 3
b110 !
b110 9
1(
#2190
0(
#2195
b1 3
1(
#2200
0(
#2205
11
b10 3
1(
#2210
0(
#2215
b111 !
b111 9
01
b0 3
1(
#2220
0(
#2225
b1 3
1(
#2230
0(
#2235
11
b10 3
1(
#2240
0(
#2245
01
b0 3
b1000 !
b1000 9
1(
#2250
0(
#2255
b1 3
1(
#2260
0(
#2265
11
b10 3
1(
#2270
0(
#2275
10
b1001 !
b1001 9
01
b0 3
1(
#2280
0(
#2285
b1 3
1(
#2290
0(
#2295
11
b10 3
1(
#2300
0(
#2305
01
b0 3
b1 "
b1 8
00
b0 !
b0 9
1(
#2310
0(
#2315
b1 3
1(
#2320
0(
#2325
11
b10 3
1(
#2330
0(
#2335
b1 !
b1 9
01
b0 3
1(
#2340
0(
#2345
b1 3
1(
#2350
0(
#2355
11
b10 3
1(
#2360
0(
#2365
01
b0 3
b10 !
b10 9
1(
#2370
0(
#2375
b1 3
1(
#2380
0(
#2385
11
b10 3
1(
#2390
0(
#2395
b11 !
b11 9
01
b0 3
1(
#2400
0(
#2405
b1 3
1(
#2410
0(
#2415
11
b10 3
1(
#2420
0(
#2425
01
b0 3
b100 !
b100 9
1(
#2430
0(
#2435
b1 3
1(
#2440
0(
#2445
11
b10 3
1(
#2450
0(
#2455
b101 !
b101 9
01
b0 3
1(
#2460
0(
#2465
b1 3
1(
#2470
0(
#2475
11
b10 3
1(
#2480
0(
#2485
01
b0 3
b110 !
b110 9
1(
#2490
0(
#2495
b1 3
1(
#2500
0(
#2505
11
b10 3
1(
#2510
0(
#2515
b111 !
b111 9
01
b0 3
1(
#2520
0(
#2525
b1 3
1(
#2530
0(
#2535
11
b10 3
1(
#2540
0(
#2545
01
b0 3
b1000 !
b1000 9
1(
#2550
0(
#2555
b1 3
1(
#2560
0(
#2565
11
b10 3
1(
#2570
0(
#2575
10
b1001 !
b1001 9
01
b0 3
1(
#2580
0(
#2585
b1 3
1(
#2590
0(
#2595
11
b10 3
1(
#2600
0(
#2605
01
b0 3
b10 "
b10 8
00
b0 !
b0 9
1(
#2610
0(
#2615
b1 3
1(
#2620
0(
#2625
11
b10 3
1(
#2630
0(
#2635
b1 !
b1 9
01
b0 3
1(
#2640
0(
#2645
b1 3
1(
#2650
0(
#2655
11
b10 3
1(
#2660
0(
#2665
01
b0 3
b10 !
b10 9
1(
#2670
0(
#2675
b1 3
1(
#2680
0(
#2685
11
b10 3
1(
#2690
0(
#2695
b11 !
b11 9
01
b0 3
1(
#2700
0(
#2705
b1 3
1(
#2710
0(
#2715
11
b10 3
1(
#2720
0(
#2725
01
b0 3
b100 !
b100 9
1(
#2730
0(
#2735
b1 3
1(
#2740
0(
#2745
11
b10 3
1(
#2750
0(
#2755
b101 !
b101 9
01
b0 3
1(
#2760
0(
#2765
b1 3
1(
#2770
0(
#2775
11
b10 3
1(
#2780
0(
#2785
01
b0 3
b110 !
b110 9
1(
#2790
0(
#2795
b1 3
1(
#2800
0(
#2805
11
b10 3
1(
#2810
0(
#2815
b111 !
b111 9
01
b0 3
1(
#2820
0(
#2825
b1 3
1(
#2830
0(
#2835
11
b10 3
1(
#2840
0(
#2845
01
b0 3
b1000 !
b1000 9
1(
#2850
0(
#2855
b1 3
1(
#2860
0(
#2865
11
b10 3
1(
#2870
0(
#2875
10
b1001 !
b1001 9
01
b0 3
1(
#2880
0(
#2885
b1 3
1(
#2890
0(
#2895
11
b10 3
1(
#2900
0(
#2905
01
b0 3
b11 "
b11 8
00
b0 !
b0 9
1(
#2910
0(
#2915
b1 3
1(
#2920
0(
#2925
11
b10 3
1(
#2930
0(
#2935
b1 !
b1 9
01
b0 3
1(
#2940
0(
#2945
b1 3
1(
#2950
0(
#2955
11
b10 3
1(
#2960
0(
#2965
01
b0 3
b10 !
b10 9
1(
#2970
0(
#2975
b1 3
1(
#2980
0(
#2985
11
b10 3
1(
#2990
0(
#2995
b11 !
b11 9
01
b0 3
1(
#3000
0(
#3005
b1 3
1(
#3010
0(
#3015
11
b10 3
1(
#3020
0(
#3025
01
b0 3
b100 !
b100 9
1(
#3030
0(
#3035
b1 3
1(
#3040
0(
#3045
11
b10 3
1(
#3050
0(
#3055
b101 !
b101 9
01
b0 3
1(
#3060
0(
#3065
b1 3
1(
#3070
0(
#3075
11
b10 3
1(
#3080
0(
#3085
01
b0 3
b110 !
b110 9
1(
#3090
0(
#3095
b1 3
1(
#3100
0(
#3105
11
b10 3
1(
#3110
0(
#3115
b111 !
b111 9
01
b0 3
1(
#3120
0(
#3125
b1 3
1(
#3130
0(
#3135
11
b10 3
1(
#3140
0(
#3145
01
b0 3
b1000 !
b1000 9
1(
#3150
0(
#3155
b1 3
1(
#3160
0(
#3165
11
b10 3
1(
#3170
0(
#3175
10
b1001 !
b1001 9
01
b0 3
1(
#3180
0(
#3185
b1 3
1(
#3190
0(
#3195
11
b10 3
1(
#3200
0(
#3205
01
b0 3
b100 "
b100 8
00
b0 !
b0 9
1(
#3210
0(
#3215
b1 3
1(
#3220
0(
#3225
11
b10 3
1(
#3230
12
1'
0(
#3235
b0 "
b0 8
b0 #
b0 7
01
b0 3
1(
#3239
0'
#3240
0(
#3245
02
1(
#3250
0(
#3255
b1 3
1(
#3260
0(
#3265
11
b10 3
1(
#3270
0(
#3275
b1 !
b1 9
01
b0 3
1(
#3280
0(
#3285
b1 3
1(
#3290
0(
#3295
11
b10 3
1(
#3300
0(
#3305
01
b0 3
b10 !
b10 9
1(
#3310
0(
#3315
b1 3
1(
#3320
0(
#3325
11
b10 3
1(
#3330
0(
#3335
b11 !
b11 9
01
b0 3
1(
#3340
0(
#3345
b1 3
1(
#3350
0(
#3355
11
b10 3
1(
#3360
0(
#3365
01
b0 3
b100 !
b100 9
1(
#3370
0(
#3375
b1 3
1(
#3380
0(
#3385
11
b10 3
1(
#3390
0(
#3395
b101 !
b101 9
01
b0 3
1(
#3400
0(
#3405
b1 3
1(
#3410
0(
#3415
11
b10 3
1(
#3420
0(
#3425
01
b0 3
b110 !
b110 9
1(
#3430
0(
#3435
b1 3
1(
#3440
0(
#3445
11
b10 3
1(
#3450
0(
#3455
b111 !
b111 9
01
b0 3
1(
#3460
0(
#3465
b1 3
1(
#3470
0(
#3475
11
b10 3
1(
#3480
0(
#3485
01
b0 3
b1000 !
b1000 9
1(
#3490
0(
#3495
b1 3
1(
#3500
0(
#3505
11
b10 3
1(
#3510
0(
#3515
10
b1001 !
b1001 9
01
b0 3
1(
#3520
0(
#3525
b1 3
1(
#3530
0(
#3535
11
b10 3
1(
#3540
0(
#3545
01
b0 3
b1 "
b1 8
00
b0 !
b0 9
1(
#3550
0(
#3555
b1 3
1(
#3560
0(
#3565
11
b10 3
1(
#3570
0(
#3575
b1 !
b1 9
01
b0 3
1(
#3580
0(
#3585
b1 3
1(
#3590
0(
#3595
11
b10 3
1(
#3600
0(
#3605
01
b0 3
b10 !
b10 9
1(
#3610
0(
#3615
b1 3
1(
#3620
0(
#3625
11
b10 3
1(
#3630
0(
#3635
b11 !
b11 9
01
b0 3
1(
#3640
0(
#3645
b1 3
1(
#3650
0(
#3655
11
b10 3
1(
#3660
0(
#3665
01
b0 3
b100 !
b100 9
1(
#3670
0(
#3675
b1 3
1(
#3680
0(
#3685
11
b10 3
1(
#3690
0(
#3695
b101 !
b101 9
01
b0 3
1(
#3700
0(
#3705
b1 3
1(
#3710
0(
#3715
11
b10 3
1(
#3720
0(
#3725
01
b0 3
b110 !
b110 9
1(
#3730
0(
#3735
b1 3
1(
#3740
0(
#3745
11
b10 3
1(
#3750
0(
#3755
b111 !
b111 9
01
b0 3
1(
#3760
0(
#3765
b1 3
1(
#3770
0(
#3775
11
b10 3
1(
#3780
0(
#3785
01
b0 3
b1000 !
b1000 9
1(
#3790
0(
#3795
b1 3
1(
#3800
0(
#3805
11
b10 3
1(
#3810
0(
#3815
10
b1001 !
b1001 9
01
b0 3
1(
#3820
0(
#3825
b1 3
1(
#3830
0(
#3835
11
b10 3
1(
#3840
0(
#3845
01
b0 3
b10 "
b10 8
00
b0 !
b0 9
1(
#3850
0(
#3855
b1 3
1(
#3860
0(
#3865
11
b10 3
1(
#3870
0(
#3875
b1 !
b1 9
01
b0 3
1(
#3880
0(
#3885
b1 3
1(
#3890
0(
#3895
11
b10 3
1(
#3900
0(
#3905
01
b0 3
b10 !
b10 9
1(
#3910
0(
#3915
b1 3
1(
#3920
0(
#3925
11
b10 3
1(
#3930
0(
#3935
b11 !
b11 9
01
b0 3
1(
#3940
0(
#3945
b1 3
1(
#3950
0(
#3955
11
b10 3
1(
#3960
0(
#3965
01
b0 3
b100 !
b100 9
1(
#3970
0(
#3975
b1 3
1(
#3980
0(
#3985
11
b10 3
1(
#3990
0(
#3995
b101 !
b101 9
01
b0 3
1(
#4000
0(
#4005
b1 3
1(
#4010
0(
#4015
11
b10 3
1(
#4020
0(
#4025
01
b0 3
b110 !
b110 9
1(
#4030
0(
#4035
b1 3
1(
#4040
0(
#4045
11
b10 3
1(
#4050
0(
#4055
b111 !
b111 9
01
b0 3
1(
#4060
0(
#4065
b1 3
1(
#4070
0(
#4075
11
b10 3
1(
#4080
0(
#4085
01
b0 3
b1000 !
b1000 9
1(
#4090
0(
#4095
b1 3
1(
#4100
0(
#4105
11
b10 3
1(
#4110
0(
#4115
10
b1001 !
b1001 9
01
b0 3
1(
#4120
0(
#4125
b1 3
1(
#4130
0(
#4135
11
b10 3
1(
#4140
0(
#4145
01
b0 3
b11 "
b11 8
00
b0 !
b0 9
1(
#4150
0(
#4155
b1 3
1(
#4160
0(
#4165
11
b10 3
1(
#4170
0(
#4175
b1 !
b1 9
01
b0 3
1(
#4180
0(
#4185
b1 3
1(
#4190
0(
#4195
11
b10 3
1(
#4200
0(
#4205
01
b0 3
b10 !
b10 9
1(
#4210
0(
#4215
b1 3
1(
#4220
0(
#4225
11
b10 3
1(
#4230
0(
#4235
b11 !
b11 9
01
b0 3
1(
#4240
0(
#4245
b1 3
1(
#4250
0(
#4255
11
b10 3
1(
#4260
0(
#4265
01
b0 3
b100 !
b100 9
1(
#4270
0(
#4275
b1 3
1(
#4280
0(
#4285
11
b10 3
1(
#4290
0(
#4295
b101 !
b101 9
01
b0 3
1(
#4300
0(
#4305
b1 3
1(
#4310
0(
#4315
11
b10 3
1(
#4320
0(
#4325
01
b0 3
b110 !
b110 9
1(
#4330
0(
#4335
b1 3
1(
#4340
0(
#4345
11
b10 3
1(
#4350
0(
#4355
b111 !
b111 9
01
b0 3
1(
#4360
0(
#4365
b1 3
1(
#4370
0(
#4375
11
b10 3
1(
#4380
0(
#4385
01
b0 3
b1000 !
b1000 9
1(
#4390
0(
#4395
b1 3
1(
#4400
0(
#4405
11
b10 3
1(
#4410
0(
#4415
10
b1001 !
b1001 9
01
b0 3
1(
#4420
0(
#4425
b1 3
1(
#4430
0(
#4435
11
b10 3
1(
#4440
0(
#4445
01
b0 3
b100 "
b100 8
00
b0 !
b0 9
1(
#4450
0(
#4455
b1 3
1(
#4460
0(
#4465
11
b10 3
1(
#4470
0(
#4475
b1 !
b1 9
01
b0 3
1(
#4480
0(
#4485
b1 3
1(
#4490
0(
#4495
11
b10 3
1(
#4500
0(
#4505
01
b0 3
b10 !
b10 9
1(
#4510
0(
#4515
b1 3
1(
#4520
0(
#4525
11
b10 3
1(
#4530
0(
#4535
b11 !
b11 9
01
b0 3
1(
#4540
0(
#4545
b1 3
1(
#4550
0(
#4555
11
b10 3
1(
#4560
0(
#4565
01
b0 3
b100 !
b100 9
1(
#4570
0(
#4575
b1 3
1(
#4580
0(
#4585
11
b10 3
1(
#4590
0(
#4595
b101 !
b101 9
01
b0 3
1(
#4600
0(
#4605
b1 3
1(
#4610
0(
#4615
11
b10 3
1(
#4620
0(
#4625
01
b0 3
b110 !
b110 9
1(
#4630
0(
#4635
b1 3
1(
#4640
0(
#4645
11
b10 3
1(
#4650
0(
#4655
b111 !
b111 9
01
b0 3
1(
#4660
0(
#4665
b1 3
1(
#4670
0(
#4675
11
b10 3
1(
#4680
0(
#4685
01
b0 3
b1000 !
b1000 9
1(
#4690
0(
#4695
b1 3
1(
#4700
0(
#4705
11
b10 3
1(
#4710
0(
#4715
10
b1001 !
b1001 9
01
b0 3
1(
#4720
0(
#4725
b1 3
1(
#4730
0(
#4735
11
b10 3
1(
#4740
0(
#4745
01
b0 3
b101 "
b101 8
00
b0 !
b0 9
1(
#4750
0(
#4755
b1 3
1(
#4760
0(
#4765
11
b10 3
1(
#4770
0(
#4775
b1 !
b1 9
01
b0 3
1(
#4780
0(
#4785
b1 3
1(
#4790
0(
#4795
11
b10 3
1(
#4800
0(
#4805
01
b0 3
b10 !
b10 9
1(
#4810
0(
#4815
b1 3
1(
#4820
0(
#4825
11
b10 3
1(
#4830
0(
#4835
b11 !
b11 9
01
b0 3
1(
#4840
0(
#4845
b1 3
1(
#4850
0(
#4855
11
b10 3
1(
#4860
0(
#4865
01
b0 3
b100 !
b100 9
1(
#4870
0(
#4875
b1 3
1(
#4880
0(
#4885
11
b10 3
1(
#4890
0(
#4895
b101 !
b101 9
01
b0 3
1(
#4900
0(
#4905
b1 3
1(
#4910
0(
#4915
11
b10 3
1(
#4920
0(
#4925
01
b0 3
b110 !
b110 9
1(
#4930
0(
#4935
b1 3
1(
#4940
0(
#4945
11
b10 3
1(
#4950
0(
#4955
b111 !
b111 9
01
b0 3
1(
#4960
0(
#4965
b1 3
1(
#4970
0(
#4975
11
b10 3
1(
#4980
0(
#4985
01
b0 3
b1000 !
b1000 9
1(
#4990
0(
#4995
b1 3
1(
#5000
0(
#5005
11
b10 3
1(
#5010
0(
#5015
1/
10
b1001 !
b1001 9
01
b0 3
1(
#5020
0(
#5025
b1 3
1(
#5030
0(
#5035
11
b10 3
1(
#5040
0(
#5045
0/
01
b0 3
b1 #
b1 7
b0 "
b0 8
00
b0 !
b0 9
1(
#5050
0(
#5055
b1 3
1(
#5060
0(
#5065
11
b10 3
1(
#5070
0(
#5075
b1 !
b1 9
01
b0 3
1(
#5080
0(
#5085
b1 3
1(
#5090
0(
#5095
11
b10 3
1(
#5100
0(
#5105
01
b0 3
b10 !
b10 9
1(
#5110
0(
#5115
b1 3
1(
#5120
0(
#5125
11
b10 3
1(
#5130
0(
#5135
b11 !
b11 9
01
b0 3
1(
#5140
0(
#5145
b1 3
1(
#5150
0(
#5155
11
b10 3
1(
#5160
0(
#5165
01
b0 3
b100 !
b100 9
1(
#5170
0(
#5175
b1 3
1(
#5180
0(
#5185
11
b10 3
1(
#5190
0(
#5195
b101 !
b101 9
01
b0 3
1(
#5200
0(
#5205
b1 3
1(
#5210
0(
#5215
11
b10 3
1(
#5220
0(
#5225
01
b0 3
b110 !
b110 9
1(
#5230
0(
#5235
b1 3
1(
#5240
0(
#5245
11
b10 3
1(
#5250
0(
