sram_ctr_ahb/src/S011HD1P_BW.v
module S011HD1P_BW(
    Q, CLK, CEN, WEN, BWEN, A, D
);
parameter Bits = 32;
parameter Word_Depth = 4096;
parameter Add_Width = 12;
parameter Wen_Width = 32;

output reg [Bits-1:0] Q;
input                 CLK;
input                 CEN;
input                 WEN;
input [Wen_Width-1:0] BWEN;
input [Add_Width-1:0] A;		//address
input [Bits-1:0]      D;		//data_write input 

wire					cen  = ~CEN;
wire					wen  = ~WEN;
wire [Wen_Width-1:0]	bwen = ~BWEN;

reg [Bits-1:0] ram [0:Word_Depth-1];

always @(posedge CLK) begin
    if(cen && wen) begin
        ram[A]	<= (D & bwen) | (ram[A] & ~bwen);
    end
		Q <= cen && !wen ? ram[A] : Q;
end

endmodule

sram_ctr_ahb/src/sram_ctr_ahb.v
module sram_ctr_ahb(
    input				hclk,
    input				hresetn,
    input				hwrite,		//0读 1写
    input	[1:0]		htrans,
    input	[2:0]		hsize,		//数据位宽 8,16,32(010)
    input	[31:0]		haddr,
    input	[2:0]		hburst,
    input	[31:0]		hwdata,
    output				hready,
    output	[1:0]		hresp,
    output	[31:0]		hrdata,
	
    output				sram_csn,
    output				sram_wen,
    output	[11:0]		sram_a,
    output	[31:0]		sram_d,
    input	[31:0]		sram_q
);

	reg [3:0]	state;
	parameter	[3:0]	IDLE	= 4'b0000;
	parameter	[3:0]	REG_W	= 4'b0001;
	parameter	[3:0]	RAW		= 4'b0010;
	parameter	[3:0]	BURST_W	= 4'b0010;
	wire state_idle		= state == IDLE;
	wire state_reg_w	= state == REG_W;

	wire trans_idle		= htrans == 2'b00;
	wire trans_noseq	= htrans == 2'b10;
	wire trans_busy		= htrans == 2'b01;

	wire burst_incr		= hburst == 3'b001;
	wire burst_single	= hburst == 3'b000;

	reg			sram_ready;
	reg	[31:0]	addr_reg;
	reg			wen_reg;

	always@(posedge hclk)begin
		if(!hresetn)begin
			state		<= IDLE;
			sram_ready	<= 1'b1;
			addr_reg	<= 0;
			wen_reg		<= 0;
		end
		else begin
			case(state)
				IDLE: begin
					if(trans_noseq && hwrite)begin
						state		<= REG_W;
						wen_reg		<= 1'b1;
						addr_reg	<= haddr;
						sram_ready	<= 1'b1;
					end	
					else begin	
						sram_ready	<= 1'b1; 
					end
				end
				REG_W: begin
					if(trans_idle)begin
						state		<= IDLE;
					end
					else if(trans_busy)begin
						wen_reg		<= 0;
					end
					else if(hwrite)begin
						state		<= REG_W;
						wen_reg		<= 1'b1;
						addr_reg	<= haddr;
						sram_ready	<= 1'b1;
					end
					else if(!hwrite)begin
						state		<= RAW;
						wen_reg		<= 0;
						addr_reg	<= haddr;
						sram_ready	<= 0;
					end
				end
				RAW: begin
						state		<= IDLE;	
						addr_reg	<= haddr;
						sram_ready	<= 1'b1;
				end
				default: ;
			endcase
		end
	end

	assign	sram_csn	=	1'b1;
	assign	sram_wen	=	state_reg_w ? wen_reg : 0;
	assign	sram_a		=	state_idle ? haddr[13:2] : addr_reg[13:2];
	assign	sram_d		=	hwdata;
		
	assign	hready		= sram_ready;
	assign	hrdata		= sram_q;
	assign	hresp		= 0; 

endmodule

sram_ctr_ahb/src/sram_ctr_ahb_tb.v
`timescale 1ps/1ps
module sram_ctr_ahb_tb();
	parameter	[1:0]	IDLE	= 2'b00;
	parameter	[1:0]	BUSY	= 2'b01;
	parameter	[1:0]	NOSEQ	= 2'b10;
	parameter	[1:0]	SEQ		= 2'b11;

	reg			hclk;
    reg			hresetn;
    reg			hwrite;
    reg [1:0]	htrans;
    reg [2:0]	hsize;
    reg [31:0]	haddr;
    reg [2:0]	hburst;
    reg [31:0]	hwdata;
    wire		hready;
    wire [1:0]	hresp;
    wire [31:0]	hrdata;
    wire		sram_csn;
    wire		sram_wen;
    wire [11:0] sram_a;
    wire [31:0] sram_d;
    wire [31:0] sram_q;

	initial begin
		$dumpfile("../sram_ctr_ahb_tb.vcd");
		$dumpvars;
	end

    initial begin
        hclk	<= 1'b1;
        hresetn <= 1'b0;

		hwrite	<= 1'b1;
        haddr	<= 32'h0000_3ff0;
        htrans	<= NOSEQ;
		hburst	<= 3'b000;
        hsize	<= 3'b010;
        hwdata	<= 32'h00000000;
        #13
        hresetn	<= 1'b1;
		#7

		#1
		haddr	<= 32'h0000_3ffc;
		hwdata	<= 32'h1010_0101;
		#10

        hwdata	<= 32'h20200202;
		
		hwrite	<= 1'b0;
        haddr	<= 32'h0000_3ffc;
        htrans	<= NOSEQ;
		hburst	<= 3'b000;
        #10
		hwrite	<= 1'b0;
        haddr	<= 32'h0000_3ff0;
        htrans	<= NOSEQ;
		hburst	<= 3'b000;
		#10
		#10
		htrans	<= IDLE;
		#10

		hwrite	<= 1'b1;
        haddr	<= 32'h0000_0010;
        htrans	<= NOSEQ;
		hburst	<= 3'b001;
        hsize	<= 3'b010;
        hwdata	<= 32'h00000000;
		#10

		hwrite	<= 1'b1;
		haddr	<= 32'h0000_0014;
		htrans	<= SEQ;	
		hburst	<= 3'b001;
		hsize	<= 3'b010;
		hwdata	<= 32'h1111_1111;
		#10

		hwrite	<= 1'b1;
		haddr	<= 32'h0000_0018;
		htrans	<= SEQ;	
		hburst	<= 3'b001;
		hsize	<= 3'b010;
		hwdata	<= 32'h2222_2222;
		#10

		hwrite	<= 1'b1;
		haddr	<= 32'h0000_001c;
		htrans	<= SEQ;	
		hburst	<= 3'b001;
		hsize	<= 3'b010;
		hwdata	<= 32'h3333_3333;
		#10

		hwrite	<= 1'b0;
		haddr	<= 32'h0000_0010;
		htrans	<= NOSEQ;	
		hburst	<= 3'b001;
		hsize	<= 3'b010;
		hwdata	<= 32'h4444_4444;
		#10

		hwrite	<= 1'b0;
		haddr	<= 32'h0000_0014;
		htrans	<= SEQ;	
		hburst	<= 3'b001;
		hsize	<= 3'b010;
		hwdata	<= 32'h0;
		#10
		#10

		hwrite	<= 1'b0;
		haddr	<= 32'h0000_0018;
		htrans	<= SEQ;	
		hburst	<= 3'b001;
		hsize	<= 3'b010;
		#10

		hwrite	<= 1'b0;
		haddr	<= 32'h0000_001c;
		htrans	<= SEQ;	
		hburst	<= 3'b001;
		hsize	<= 3'b010;
		#10
		
		hwrite	<= 1'b0;
		haddr	<= 32'h0000_0000;
		htrans	<= IDLE;	
		hburst	<= 3'b000;
		hsize	<= 3'b010;
		#10

		#10
		$finish;
    end

    always #5 hclk <= ~hclk;

    sram_ctr_ahb u_sram_ctrl_ahb(
        .hclk		(hclk),
        .hresetn	(hresetn),
        .hwrite		(hwrite),
        .htrans		(htrans),
        .hsize		(hsize),
        .haddr		(haddr),
        .hburst		(hburst),
        .hwdata		(hwdata),
        .hready		(hready),
        .hresp		(hresp),
        .hrdata		(hrdata),
        .sram_csn	(sram_csn),
        .sram_wen	(sram_wen),
        .sram_a		(sram_a),
        .sram_d		(sram_d),
        .sram_q		(sram_q)
    );

	S011HD1P_BW sram(
		.Q		(sram_q),
		.CLK	(hclk),
		.CEN	(~sram_csn),
		.WEN	(~sram_wen),
		.BWEN	(0),
		.A		(sram_a),
		.D		(sram_d)
	);

endmodule

sram_ctr_ahb/sim/sram_ctr_ahb_tb.vcd
$date
	Thu Jan  4 10:58:28 2024
$end
$version
	Icarus Verilog
$end
$timescale
	1ps
$end
$scope module sram_ctr_ahb_tb $end
$var wire 2 ! hresp [1:0] $end
$var wire 1 " sram_csn $end
$var wire 1 # sram_wen $end
$var wire 32 $ sram_q [31:0] $end
$var wire 32 % sram_d [31:0] $end
$var wire 12 & sram_a [11:0] $end
$var wire 1 ' hready $end
$var wire 32 ( hrdata [31:0] $end
$var reg 32 ) haddr [31:0] $end
$var reg 3 * hburst [2:0] $end
$var reg 1 + hclk $end
$var reg 1 , hresetn $end
$var reg 3 - hsize [2:0] $end
$var reg 2 . htrans [1:0] $end
$var reg 32 / hwdata [31:0] $end
$var reg 1 0 hwrite $end
$scope module sram $end
$var wire 32 1 BWEN [31:0] $end
$var wire 1 2 CEN $end
$var wire 1 + CLK $end
$var wire 1 3 WEN $end
$var wire 32 4 bwen [31:0] $end
$var wire 1 5 cen $end
$var wire 1 6 wen $end
$var wire 32 7 D [31:0] $end
$var wire 12 8 A [11:0] $end
$var reg 32 9 Q [31:0] $end
$upscope $end
$scope module u_sram_ctrl_ahb $end
$var wire 32 : haddr [31:0] $end
$var wire 3 ; hburst [2:0] $end
$var wire 1 + hclk $end
$var wire 32 < hrdata [31:0] $end
$var wire 1 ' hready $end
$var wire 1 , hresetn $end
$var wire 2 = hresp [1:0] $end
$var wire 3 > hsize [2:0] $end
$var wire 2 ? htrans [1:0] $end
$var wire 32 @ hwdata [31:0] $end
$var wire 1 0 hwrite $end
$var wire 1 " sram_csn $end
$var wire 32 A sram_d [31:0] $end
$var wire 32 B sram_q [31:0] $end
$var wire 1 C trans_noseq $end
$var wire 1 D trans_idle $end
$var wire 1 E trans_busy $end
$var wire 1 F state_reg_w $end
$var wire 1 G state_idle $end
$var wire 1 # sram_wen $end
$var wire 12 H sram_a [11:0] $end
$var wire 1 I burst_single $end
$var wire 1 J burst_incr $end
$var reg 32 K addr_reg [31:0] $end
$var reg 1 L sram_ready $end
$var reg 4 M state [3:0] $end
$var reg 1 N wen_reg $end
$upscope $end
$upscope $end
$enddefinitions $end
#0
$dumpvars
0N
b0 M
1L
b0 K
0J
1I
b111111111100 H
1G
0F
0E
0D
1C
bx B
b0 A
b0 @
b10 ?
b10 >
b0 =
bx <
b0 ;
b11111111110000 :
bx 9
b111111111100 8
b0 7
06
15
b11111111111111111111111111111111 4
13
02
b0 1
10
b0 /
b10 .
b10 -
0,
1+
b0 *
b11111111110000 )
bx (
1'
b111111111100 &
b0 %
bx $
0#
1"
b0 !
$end
#5
0+
#10
1+
#13
1,
#15
0+
#20
16
03
b111111111100 &
b111111111100 8
b111111111100 H
1#
b11111111110000 K
1N
0G
1F
b1 M
1+
#21
b10000000100000000000100000001 %
b10000000100000000000100000001 7
b10000000100000000000100000001 A
b10000000100000000000100000001 /
b10000000100000000000100000001 @
b11111111111100 )
b11111111111100 :
#25
0+
#30
b111111111111 &
b111111111111 8
b111111111111 H
b11111111111100 K
1+
#31
00
b100000001000000000001000000010 %
b100000001000000000001000000010 7
b100000001000000000001000000010 A
b100000001000000000001000000010 /
b100000001000000000001000000010 @
#35
0+
#40
06
13
0#
0'
0L
0N
0F
b10 M
1+
#41
b11111111110000 )
b11111111110000 :
#45
0+
#50
b111111111100 &
b111111111100 8
b111111111100 H
b100000001000000000001000000010 (
b100000001000000000001000000010 <
b100000001000000000001000000010 $
b100000001000000000001000000010 9
b100000001000000000001000000010 B
1'
1L
b11111111110000 K
1G
b0 M
1+
#55
0+
#60
b10000000100000000000100000001 (
b10000000100000000000100000001 <
b10000000100000000000100000001 $
b10000000100000000000100000001 9
b10000000100000000000100000001 B
1+
#61
1D
0C
b0 .
b0 ?
#65
0+
#70
1+
#71
b100 &
b100 8
b100 H
b0 %
b0 7
b0 A
b0 /
b0 @
1J
0I
b1 *
b1 ;
0D
1C
b10 .
b10 ?
b10000 )
b10000 :
10
#75
0+
#80
16
03
b100 &
b100 8
b100 H
1#
b10000 K
1N
0G
1F
b1 M
bx (
bx <
bx $
bx 9
bx B
1+
#81
b10001000100010001000100010001 %
b10001000100010001000100010001 7
b10001000100010001000100010001 A
b10001000100010001000100010001 /
b10001000100010001000100010001 @
0C
b11 .
b11 ?
b10100 )
b10100 :
#85
0+
#90
b101 &
b101 8
b101 H
b10100 K
1+
#91
b100010001000100010001000100010 %
b100010001000100010001000100010 7
b100010001000100010001000100010 A
b100010001000100010001000100010 /
b100010001000100010001000100010 @
b11000 )
b11000 :
#95
0+
#100
b110 &
b110 8
b110 H
b11000 K
1+
#101
b110011001100110011001100110011 %
b110011001100110011001100110011 7
b110011001100110011001100110011 A
b110011001100110011001100110011 /
b110011001100110011001100110011 @
b11100 )
b11100 :
#105
0+
#110
b111 &
b111 8
b111 H
b11100 K
1+
#111
b1000100010001000100010001000100 %
b1000100010001000100010001000100 7
b1000100010001000100010001000100 A
b1000100010001000100010001000100 /
b1000100010001000100010001000100 @
1C
b10 .
b10 ?
b10000 )
b10000 :
00
#115
0+
#120
06
b100 &
b100 8
b100 H
13
0#
0'
0L
b10000 K
0N
0F
b10 M
1+
#121
b0 %
b0 7
b0 A
b0 /
b0 @
0C
b11 .
b11 ?
b10100 )
b10100 :
#125
0+
#130
b101 &
b101 8
b101 H
b10001000100010001000100010001 (
b10001000100010001000100010001 <
b10001000100010001000100010001 $
b10001000100010001000100010001 9
b10001000100010001000100010001 B
1'
1L
b10100 K
1G
b0 M
1+
#135
0+
#140
b100010001000100010001000100010 (
b100010001000100010001000100010 <
b100010001000100010001000100010 $
b100010001000100010001000100010 9
b100010001000100010001000100010 B
1+
#141
b110 &
b110 8
b110 H
b11000 )
b11000 :
#145
0+
#150
b110011001100110011001100110011 (
b110011001100110011001100110011 <
b110011001100110011001100110011 $
b110011001100110011001100110011 9
b110011001100110011001100110011 B
1+
#151
b111 &
b111 8
b111 H
b11100 )
b11100 :
#155
0+
#160
b1000100010001000100010001000100 (
b1000100010001000100010001000100 <
b1000100010001000100010001000100 $
b1000100010001000100010001000100 9
b1000100010001000100010001000100 B
1+
#161
b0 &
b0 8
b0 H
0J
1I
b0 *
b0 ;
1D
b0 .
b0 ?
b0 )
b0 :
#165
0+
#170
bx (
bx <
bx $
bx 9
bx B
1+
