mat_scan/sync/mat_scan.srcs/sources_1/imports/src/sram.v
module sram #(
    parameter ADDR_DEPTH = 4,
    parameter DATA_WIDTH = 8,
    parameter DATA_DEPTH = 16
)(
	input					clk,
    input					rst_n,
    input					w_en,
    input					r_en,
    input [ADDR_DEPTH-1:0]	addr,
    input [DATA_WIDTH-1:0]	din,
    output reg [DATA_WIDTH-1:0] dout
);
    
    reg [DATA_WIDTH-1:0] mem [DATA_DEPTH-1:0];

    integer i;
	always @(posedge clk) begin
        if (!rst_n)begin
            for (i = 0; i < DATA_DEPTH; i=i+1) begin
                mem[i] <= 0;
            end
        end
        else if (w_en) begin
            mem[addr] <= din;
        end
    end

    always @(posedge clk) begin
        if (!rst_n) begin
            dout <= 0;
        end
        else if (r_en) begin
            dout <= mem[addr];
        end
    end

endmodule

mat_scan/src/mat_scan.v
module mat_scan(
	input				clk,
	input				rst_n,
	input				vld_in,
	input		[9:0]	din,
	output	reg			vld_out,
	output	reg [9:0]	dout
);
	reg [2:0]	state;
	parameter [2:0]	IDLE	= 3'b000;
	parameter [2:0]	DATA_IN	= 3'b001;
	parameter [2:0]	DATA_OUT= 3'b010;
	parameter [2:0]	WAIT	= 3'b011;

	reg	[5:0]	addr;
	reg			r_en;
	reg [5:0]	cnt;
	wire [9:0]	d_o;

	always@(posedge clk)begin
		if(!rst_n)begin
			state	<= 0;
			addr	<= 0;
			r_en	<= 0;
			cnt		<= 0;
			vld_out	<= 0;
			dout	<= 0;
		end
		else begin
			case(state)
				IDLE:begin
					if(vld_in)begin
						state	<= DATA_IN;
						addr	<= 1;
						cnt		<= 6'd63; 
					end
					else begin	
						addr		<= 0;
						vld_out		<= 0;
						dout		<= 0;
					end
				end
				DATA_IN:begin
					if(cnt == 0)begin
						state	<= WAIT;
						r_en	<= 1'b1;
						addr	<= 0;
						cnt		<= 6'd63;
					end
					else begin
						addr	<= addr + 6'd1;
						cnt		<= cnt - 6'd1;
					end
				end
				WAIT:begin
					state	<= DATA_OUT;
					addr	<= addr + 1;
				end
				DATA_OUT:begin
					if(cnt == 0)begin
						state	<= IDLE;
						addr	<= 0;
						r_en	<= 0;
						vld_out	<= 1'b1;
						dout	<= d_o;
					end
					else begin
						vld_out	<= 1'b1;
						dout	<= d_o;
						cnt		<= cnt - 6'd1;
						case(addr)
							6'b00_0000: addr <= 6'b00_0001;
                			6'b00_0001: addr <= 6'b00_1000;
                			6'b00_1000: addr <= 6'b01_0000;
                			6'b01_0000: addr <= 6'b00_1001;
                			6'b00_1001: addr <= 6'b00_0010;
                			6'b00_0010: addr <= 6'b00_0011;
                			6'b00_0011: addr <= 6'b00_1010;
                			6'b00_1010: addr <= 6'b01_0001;
                			6'b01_0001: addr <= 6'b01_1000;
                			6'b01_1000: addr <= 6'b10_0000;
                			6'b10_0000: addr <= 6'b01_1001;
                			6'b01_1001: addr <= 6'b01_0010;
                			6'b01_0010: addr <= 6'b00_1011;
                			6'b00_1011: addr <= 6'b00_0100;
                			6'b00_0100: addr <= 6'b00_0101;
                			6'b00_0101: addr <= 6'b00_1100;
                			6'b00_1100: addr <= 6'b01_0011;
                			6'b01_0011: addr <= 6'b01_1010;
                			6'b01_1010: addr <= 6'b10_0001;
                			6'b10_0001: addr <= 6'b10_1000;
                			6'b10_1000: addr <= 6'b11_0000;
                			6'b11_0000: addr <= 6'b10_1001;
                			6'b10_1001: addr <= 6'b10_0010;
                			6'b10_0010: addr <= 6'b01_1011;
                			6'b01_1011: addr <= 6'b01_0100;
                			6'b01_0100: addr <= 6'b00_1101;
                			6'b00_1101: addr <= 6'b00_0110;
                			6'b00_0110: addr <= 6'b00_0111;
                			6'b00_0111: addr <= 6'b00_1110;
                			6'b00_1110: addr <= 6'b01_0101;
                			6'b01_0101: addr <= 6'b01_1100;
                			6'b01_1100: addr <= 6'b10_0011;
                			6'b10_0011: addr <= 6'b10_1010;
                			6'b10_1010: addr <= 6'b11_0001;
                			6'b11_0001: addr <= 6'b11_1000;
                			6'b11_1000: addr <= 6'b11_1001;
                			6'b11_1001: addr <= 6'b11_0010;
                			6'b11_0010: addr <= 6'b10_1011;
                			6'b10_1011: addr <= 6'b10_0100;
                			6'b10_0100: addr <= 6'b01_1101;
                			6'b01_1101: addr <= 6'b01_0110;
                			6'b01_0110: addr <= 6'b00_1111;
                			6'b00_1111: addr <= 6'b01_0111;
                			6'b01_0111: addr <= 6'b01_1110;
                			6'b01_1110: addr <= 6'b10_0101;
                			6'b10_0101: addr <= 6'b10_1100;
                			6'b10_1100: addr <= 6'b11_0011;
                			6'b11_0011: addr <= 6'b11_1010;
                			6'b11_1010: addr <= 6'b11_1011;
                			6'b11_1011: addr <= 6'b11_0100;
                			6'b11_0100: addr <= 6'b10_1101;
                			6'b10_1101: addr <= 6'b10_0110;
                			6'b10_0110: addr <= 6'b01_1111;
                			6'b01_1111: addr <= 6'b10_0111;
                			6'b10_0111: addr <= 6'b10_1110;
                			6'b10_1110: addr <= 6'b11_0101;
                			6'b11_0101: addr <= 6'b11_1100;
                			6'b11_1100: addr <= 6'b11_1101;
                			6'b11_1101: addr <= 6'b11_0110;
                			6'b11_0110: addr <= 6'b10_1111;
                			6'b10_1111: addr <= 6'b11_0111;
                			6'b11_0111: addr <= 6'b11_1110;
                			6'b11_1110: addr <= 6'b11_1111;
							6'b11_1111: addr <= 6'b00_0000;
							default: ;
						endcase
					end
				end
				default: ;
			endcase
		end
	end

	sram #(
		.ADDR_DEPTH(6),
        .DATA_WIDTH(10),
        .DATA_DEPTH(64)	
	)sram(
		.clk		(clk),
        .rst_n		(rst_n),
        .w_en		(vld_in),
        .r_en		(r_en),
        .addr		(addr),
        .din		(din),
        .dout		(d_o)
	);
endmodule

mat_scan/src/mat_scan_tb.v
`timescale 1ps/1ps
module mat_scan_tb();
    reg			clk, rst_n, vld_in;
    reg [9:0]	din;
    wire		vld_out;
    wire [9:0] dout;

	reg	[6:0]	cnt;

	initial begin        
        $dumpfile("../mat_scan_tb.vcd");
        $dumpvars;           
    end      
    initial begin
        clk		<= 0;
        rst_n	<= 0;
        din		<= 0;
        vld_in	<= 0;
		cnt		<= 7'd64;
        #3
        rst_n	<= 1'b1;
		#300
		$finish;
    end

    always #1 clk <= ~clk;

    always @(posedge clk) begin
		if(rst_n)begin
			if (cnt == 0)begin
				vld_in	<= 0;
			end
			else begin
				vld_in	<= 1'b1;
				din		<= din + 1'b1;
				cnt		<= cnt - 6'd1;
        	end
		end
    end

    mat_scan u_mat_scan(
        .clk		(clk),
        .rst_n		(rst_n),
        .vld_in		(vld_in),
        .din		(din),
        .vld_out	(vld_out),
        .dout		(dout)
    );

endmodule

mat_scan/sim/mat_scan_tb.vcd
$date
	Mon Jan  1 18:26:05 2024
$end
$version
	Icarus Verilog
$end
$timescale
	1ps
$end
$scope module mat_scan_tb $end
$var wire 1 ! vld_out $end
$var wire 10 " dout [9:0] $end
$var reg 1 # clk $end
$var reg 7 $ cnt [6:0] $end
$var reg 10 % din [9:0] $end
$var reg 1 & rst_n $end
$var reg 1 ' vld_in $end
$scope module u_mat_scan $end
$var wire 1 # clk $end
$var wire 10 ( din [9:0] $end
$var wire 1 & rst_n $end
$var wire 1 ' vld_in $end
$var wire 10 ) d_o [9:0] $end
$var reg 6 * addr [5:0] $end
$var reg 6 + cnt [5:0] $end
$var reg 10 , dout [9:0] $end
$var reg 1 - r_en $end
$var reg 3 . state [2:0] $end
$var reg 1 ! vld_out $end
$scope module sram $end
$var wire 6 / addr [5:0] $end
$var wire 1 # clk $end
$var wire 10 0 din [9:0] $end
$var wire 1 - r_en $end
$var wire 1 & rst_n $end
$var wire 1 ' w_en $end
$var reg 10 1 dout [9:0] $end
$var integer 32 2 i [31:0] $end
$upscope $end
$upscope $end
$upscope $end
$enddefinitions $end
#0
$dumpvars
bx 2
bx 1
b0 0
bx /
bx .
x-
bx ,
bx +
bx *
bx )
b0 (
0'
0&
b0 %
b1000000 $
0#
bx "
x!
$end
#1
b0 )
b0 1
b0 "
b0 ,
0!
b0 +
0-
b0 *
b0 /
b0 .
b1000000 2
1#
#2
0#
#3
b111111 $
b1 %
b1 (
b1 0
1'
1#
1&
#4
0#
#5
b111111 +
b1 *
b1 /
b1 .
b111110 $
b10 %
b10 (
b10 0
1#
#6
0#
#7
b111101 $
b11 %
b11 (
b11 0
b111110 +
b10 *
b10 /
1#
#8
0#
#9
b111101 +
b11 *
b11 /
b111100 $
b100 %
b100 (
b100 0
1#
#10
0#
#11
b111011 $
b101 %
b101 (
b101 0
b111100 +
b100 *
b100 /
1#
#12
0#
#13
b111011 +
b101 *
b101 /
b111010 $
b110 %
b110 (
b110 0
1#
#14
0#
#15
b111001 $
b111 %
b111 (
b111 0
b111010 +
b110 *
b110 /
1#
#16
0#
#17
b111001 +
b111 *
b111 /
b111000 $
b1000 %
b1000 (
b1000 0
1#
#18
0#
#19
b110111 $
b1001 %
b1001 (
b1001 0
b111000 +
b1000 *
b1000 /
1#
#20
0#
#21
b110111 +
b1001 *
b1001 /
b110110 $
b1010 %
b1010 (
b1010 0
1#
#22
0#
#23
b110101 $
b1011 %
b1011 (
b1011 0
b110110 +
b1010 *
b1010 /
1#
#24
0#
#25
b110101 +
b1011 *
b1011 /
b110100 $
b1100 %
b1100 (
b1100 0
1#
#26
0#
#27
b110011 $
b1101 %
b1101 (
b1101 0
b110100 +
b1100 *
b1100 /
1#
#28
0#
#29
b110011 +
b1101 *
b1101 /
b110010 $
b1110 %
b1110 (
b1110 0
1#
#30
0#
#31
b110001 $
b1111 %
b1111 (
b1111 0
b110010 +
b1110 *
b1110 /
1#
#32
0#
#33
b110001 +
b1111 *
b1111 /
b110000 $
b10000 %
b10000 (
b10000 0
1#
#34
0#
#35
b101111 $
b10001 %
b10001 (
b10001 0
b110000 +
b10000 *
b10000 /
1#
#36
0#
#37
b101111 +
b10001 *
b10001 /
b101110 $
b10010 %
b10010 (
b10010 0
1#
#38
0#
#39
b101101 $
b10011 %
b10011 (
b10011 0
b101110 +
b10010 *
b10010 /
1#
#40
0#
#41
b101101 +
b10011 *
b10011 /
b101100 $
b10100 %
b10100 (
b10100 0
1#
#42
0#
#43
b101011 $
b10101 %
b10101 (
b10101 0
b101100 +
b10100 *
b10100 /
1#
#44
0#
#45
b101011 +
b10101 *
b10101 /
b101010 $
b10110 %
b10110 (
b10110 0
1#
#46
0#
#47
b101001 $
b10111 %
b10111 (
b10111 0
b101010 +
b10110 *
b10110 /
1#
#48
0#
#49
b101001 +
b10111 *
b10111 /
b101000 $
b11000 %
b11000 (
b11000 0
1#
#50
0#
#51
b100111 $
b11001 %
b11001 (
b11001 0
b101000 +
b11000 *
b11000 /
1#
#52
0#
#53
b100111 +
b11001 *
b11001 /
b100110 $
b11010 %
b11010 (
b11010 0
1#
#54
0#
#55
b100101 $
b11011 %
b11011 (
b11011 0
b100110 +
b11010 *
b11010 /
1#
#56
0#
#57
b100101 +
b11011 *
b11011 /
b100100 $
b11100 %
b11100 (
b11100 0
1#
#58
0#
#59
b100011 $
b11101 %
b11101 (
b11101 0
b100100 +
b11100 *
b11100 /
1#
#60
0#
#61
b100011 +
b11101 *
b11101 /
b100010 $
b11110 %
b11110 (
b11110 0
1#
#62
0#
#63
b100001 $
b11111 %
b11111 (
b11111 0
b100010 +
b11110 *
b11110 /
1#
#64
0#
#65
b100001 +
b11111 *
b11111 /
b100000 $
b100000 %
b100000 (
b100000 0
1#
#66
0#
#67
b11111 $
b100001 %
b100001 (
b100001 0
b100000 +
b100000 *
b100000 /
1#
#68
0#
#69
b11111 +
b100001 *
b100001 /
b11110 $
b100010 %
b100010 (
b100010 0
1#
#70
0#
#71
b11101 $
b100011 %
b100011 (
b100011 0
b11110 +
b100010 *
b100010 /
1#
#72
0#
#73
b11101 +
b100011 *
b100011 /
b11100 $
b100100 %
b100100 (
b100100 0
1#
#74
0#
#75
b11011 $
b100101 %
b100101 (
b100101 0
b11100 +
b100100 *
b100100 /
1#
#76
0#
#77
b11011 +
b100101 *
b100101 /
b11010 $
b100110 %
b100110 (
b100110 0
1#
#78
0#
#79
b11001 $
b100111 %
b100111 (
b100111 0
b11010 +
b100110 *
b100110 /
1#
#80
0#
#81
b11001 +
b100111 *
b100111 /
b11000 $
b101000 %
b101000 (
b101000 0
1#
#82
0#
#83
b10111 $
b101001 %
b101001 (
b101001 0
b11000 +
b101000 *
b101000 /
1#
#84
0#
#85
b10111 +
b101001 *
b101001 /
b10110 $
b101010 %
b101010 (
b101010 0
1#
#86
0#
#87
b10101 $
b101011 %
b101011 (
b101011 0
b10110 +
b101010 *
b101010 /
1#
#88
0#
#89
b10101 +
b101011 *
b101011 /
b10100 $
b101100 %
b101100 (
b101100 0
1#
#90
0#
#91
b10011 $
b101101 %
b101101 (
b101101 0
b10100 +
b101100 *
b101100 /
1#
#92
0#
#93
b10011 +
b101101 *
b101101 /
b10010 $
b101110 %
b101110 (
b101110 0
1#
#94
0#
#95
b10001 $
b101111 %
b101111 (
b101111 0
b10010 +
b101110 *
b101110 /
1#
#96
0#
#97
b10001 +
b101111 *
b101111 /
b10000 $
b110000 %
b110000 (
b110000 0
1#
#98
0#
#99
b1111 $
b110001 %
b110001 (
b110001 0
b10000 +
b110000 *
b110000 /
1#
#100
0#
#101
b1111 +
b110001 *
b110001 /
b1110 $
b110010 %
b110010 (
b110010 0
1#
#102
0#
#103
b1101 $
b110011 %
b110011 (
b110011 0
b1110 +
b110010 *
b110010 /
1#
#104
0#
#105
b1101 +
b110011 *
b110011 /
b1100 $
b110100 %
b110100 (
b110100 0
1#
#106
0#
#107
b1011 $
b110101 %
b110101 (
b110101 0
b1100 +
b110100 *
b110100 /
1#
#108
0#
#109
b1011 +
b110101 *
b110101 /
b1010 $
b110110 %
b110110 (
b110110 0
1#
#110
0#
#111
b1001 $
b110111 %
b110111 (
b110111 0
b1010 +
b110110 *
b110110 /
1#
#112
0#
#113
b1001 +
b110111 *
b110111 /
b1000 $
b111000 %
b111000 (
b111000 0
1#
#114
0#
#115
b111 $
b111001 %
b111001 (
b111001 0
b1000 +
b111000 *
b111000 /
1#
#116
0#
#117
b111 +
b111001 *
b111001 /
b110 $
b111010 %
b111010 (
b111010 0
1#
#118
0#
#119
b101 $
b111011 %
b111011 (
b111011 0
b110 +
b111010 *
b111010 /
1#
#120
0#
#121
b101 +
b111011 *
b111011 /
b100 $
b111100 %
b111100 (
b111100 0
1#
#122
0#
#123
b11 $
b111101 %
b111101 (
b111101 0
b100 +
b111100 *
b111100 /
1#
#124
0#
#125
b11 +
b111101 *
b111101 /
b10 $
b111110 %
b111110 (
b111110 0
1#
#126
0#
#127
b1 $
b111111 %
b111111 (
b111111 0
b10 +
b111110 *
b111110 /
1#
#128
0#
#129
b1 +
b111111 *
b111111 /
b0 $
b1000000 %
b1000000 (
b1000000 0
1#
#130
0#
#131
0'
b0 +
b0 *
b0 /
1#
#132
0#
#133
b111111 +
1-
b11 .
1#
#134
0#
#135
b1 *
b1 /
b10 .
b1 )
b1 1
1#
#136
0#
#137
b10 )
b10 1
b1000 *
b1000 /
b111110 +
b1 "
b1 ,
1!
1#
#138
0#
#139
b10000 *
b10000 /
b111101 +
b10 "
b10 ,
b1001 )
b1001 1
1#
#140
0#
#141
b10001 )
b10001 1
b1001 *
b1001 /
b111100 +
b1001 "
b1001 ,
1#
#142
0#
#143
b10 *
b10 /
b111011 +
b10001 "
b10001 ,
b1010 )
b1010 1
1#
#144
0#
#145
b11 )
b11 1
b11 *
b11 /
b111010 +
b1010 "
b1010 ,
1#
#146
0#
#147
b1010 *
b1010 /
b111001 +
b11 "
b11 ,
b100 )
b100 1
1#
#148
0#
#149
b1011 )
b1011 1
b10001 *
b10001 /
b111000 +
b100 "
b100 ,
1#
#150
0#
#151
b11000 *
b11000 /
b110111 +
b1011 "
b1011 ,
b10010 )
b10010 1
1#
#152
0#
#153
b11001 )
b11001 1
b100000 *
b100000 /
b110110 +
b10010 "
b10010 ,
1#
#154
0#
#155
b11001 *
b11001 /
b110101 +
b11001 "
b11001 ,
b100001 )
b100001 1
1#
#156
0#
#157
b11010 )
b11010 1
b10010 *
b10010 /
b110100 +
b100001 "
b100001 ,
1#
#158
0#
#159
b1011 *
b1011 /
b110011 +
b11010 "
b11010 ,
b10011 )
b10011 1
1#
#160
0#
#161
b1100 )
b1100 1
b100 *
b100 /
b110010 +
b10011 "
b10011 ,
1#
#162
0#
#163
b101 *
b101 /
b110001 +
b1100 "
b1100 ,
b101 )
b101 1
1#
#164
0#
#165
b110 )
b110 1
b1100 *
b1100 /
b110000 +
b101 "
b101 ,
1#
#166
0#
#167
b10011 *
b10011 /
b101111 +
b110 "
b110 ,
b1101 )
b1101 1
1#
#168
0#
#169
b10100 )
b10100 1
b11010 *
b11010 /
b101110 +
b1101 "
b1101 ,
1#
#170
0#
#171
b100001 *
b100001 /
b101101 +
b10100 "
b10100 ,
b11011 )
b11011 1
1#
#172
0#
#173
b100010 )
b100010 1
b101000 *
b101000 /
b101100 +
b11011 "
b11011 ,
1#
#174
0#
#175
b110000 *
b110000 /
b101011 +
b100010 "
b100010 ,
b101001 )
b101001 1
1#
#176
0#
#177
b110001 )
b110001 1
b101001 *
b101001 /
b101010 +
b101001 "
b101001 ,
1#
#178
0#
#179
b100010 *
b100010 /
b101001 +
b110001 "
b110001 ,
b101010 )
b101010 1
1#
#180
0#
#181
b100011 )
b100011 1
b11011 *
b11011 /
b101000 +
b101010 "
b101010 ,
1#
#182
0#
#183
b10100 *
b10100 /
b100111 +
b100011 "
b100011 ,
b11100 )
b11100 1
1#
#184
0#
#185
b10101 )
b10101 1
b1101 *
b1101 /
b100110 +
b11100 "
b11100 ,
1#
#186
0#
#187
b110 *
b110 /
b100101 +
b10101 "
b10101 ,
b1110 )
b1110 1
1#
#188
0#
#189
b111 )
b111 1
b111 *
b111 /
b100100 +
b1110 "
b1110 ,
1#
#190
0#
#191
b1110 *
b1110 /
b100011 +
b111 "
b111 ,
b1000 )
b1000 1
1#
#192
0#
#193
b1111 )
b1111 1
b10101 *
b10101 /
b100010 +
b1000 "
b1000 ,
1#
#194
0#
#195
b11100 *
b11100 /
b100001 +
b1111 "
b1111 ,
b10110 )
b10110 1
1#
#196
0#
#197
b11101 )
b11101 1
b100011 *
b100011 /
b100000 +
b10110 "
b10110 ,
1#
#198
0#
#199
b101010 *
b101010 /
b11111 +
b11101 "
b11101 ,
b100100 )
b100100 1
1#
#200
0#
#201
b101011 )
b101011 1
b110001 *
b110001 /
b11110 +
b100100 "
b100100 ,
1#
#202
0#
#203
b111000 *
b111000 /
b11101 +
b101011 "
b101011 ,
b110010 )
b110010 1
1#
#204
0#
#205
b111001 )
b111001 1
b111001 *
b111001 /
b11100 +
b110010 "
b110010 ,
1#
#206
0#
#207
b110010 *
b110010 /
b11011 +
b111001 "
b111001 ,
b111010 )
b111010 1
1#
#208
0#
#209
b110011 )
b110011 1
b101011 *
b101011 /
b11010 +
b111010 "
b111010 ,
1#
#210
0#
#211
b100100 *
b100100 /
b11001 +
b110011 "
b110011 ,
b101100 )
b101100 1
1#
#212
0#
#213
b100101 )
b100101 1
b11101 *
b11101 /
b11000 +
b101100 "
b101100 ,
1#
#214
0#
#215
b10110 *
b10110 /
b10111 +
b100101 "
b100101 ,
b11110 )
b11110 1
1#
#216
0#
#217
b10111 )
b10111 1
b1111 *
b1111 /
b10110 +
b11110 "
b11110 ,
1#
#218
0#
#219
b10111 *
b10111 /
b10101 +
b10111 "
b10111 ,
b10000 )
b10000 1
1#
#220
0#
#221
b11000 )
b11000 1
b11110 *
b11110 /
b10100 +
b10000 "
b10000 ,
1#
#222
0#
#223
b100101 *
b100101 /
b10011 +
b11000 "
b11000 ,
b11111 )
b11111 1
1#
#224
0#
#225
b100110 )
b100110 1
b101100 *
b101100 /
b10010 +
b11111 "
b11111 ,
1#
#226
0#
#227
b110011 *
b110011 /
b10001 +
b100110 "
b100110 ,
b101101 )
b101101 1
1#
#228
0#
#229
b110100 )
b110100 1
b111010 *
b111010 /
b10000 +
b101101 "
b101101 ,
1#
#230
0#
#231
b111011 *
b111011 /
b1111 +
b110100 "
b110100 ,
b111011 )
b111011 1
1#
#232
0#
#233
b111100 )
b111100 1
b110100 *
b110100 /
b1110 +
b111011 "
b111011 ,
1#
#234
0#
#235
b101101 *
b101101 /
b1101 +
b111100 "
b111100 ,
b110101 )
b110101 1
1#
#236
0#
#237
b101110 )
b101110 1
b100110 *
b100110 /
b1100 +
b110101 "
b110101 ,
1#
#238
0#
#239
b11111 *
b11111 /
b1011 +
b101110 "
b101110 ,
b100111 )
b100111 1
1#
#240
0#
#241
b100000 )
b100000 1
b100111 *
b100111 /
b1010 +
b100111 "
b100111 ,
1#
#242
0#
#243
b101110 *
b101110 /
b1001 +
b100000 "
b100000 ,
b101000 )
b101000 1
1#
#244
0#
#245
b101111 )
b101111 1
b110101 *
b110101 /
b1000 +
b101000 "
b101000 ,
1#
#246
0#
#247
b111100 *
b111100 /
b111 +
b101111 "
b101111 ,
b110110 )
b110110 1
1#
#248
0#
#249
b111101 )
b111101 1
b111101 *
b111101 /
b110 +
b110110 "
b110110 ,
1#
#250
0#
#251
b110110 *
b110110 /
b101 +
b111101 "
b111101 ,
b111110 )
b111110 1
1#
#252
0#
#253
b110111 )
b110111 1
b101111 *
b101111 /
b100 +
b111110 "
b111110 ,
1#
#254
0#
#255
b110111 *
b110111 /
b11 +
b110111 "
b110111 ,
b110000 )
b110000 1
1#
#256
0#
#257
b111000 )
b111000 1
b111110 *
b111110 /
b10 +
b110000 "
b110000 ,
1#
#258
0#
#259
b111111 *
b111111 /
b1 +
b111000 "
b111000 ,
b111111 )
b111111 1
1#
#260
0#
#261
b1000000 )
b1000000 1
b0 *
b0 /
b0 +
b111111 "
b111111 ,
1#
#262
0#
#263
b1000000 "
b1000000 ,
0-
b0 .
b1 )
b1 1
1#
#264
0#
#265
b0 "
b0 ,
0!
1#
