sqrt_u32/src/sqrt_u32.v
module partial_cal(
	input	[31:0]	x_i,
	input			valid_i,
	input	[15:0]	q_i,
	input	[16:0]	s_i,

	output	[31:0]	x_o,
	output			valid_o,
	output	[15:0]	q_o,
	output	[16:0]	s_o
);
	wire [17:0]	tmp = (q_i << 2) + 1;
	wire [16:0]	diff = s_i - tmp;
	
	assign x_o		= x_i << 2;
	assign valid_o	= valid_i;
	assign q_o		= (!(tmp > s_i)) ? {q_i[14:0] , 1'b1} : {q_i[14:0] , 1'b0};
	assign s_o		= (!(tmp > s_i)) ? {diff[14:0],x_i[29:28]} : {s_i[14:0],x_i[29:28]};
	
endmodule

// top module
module sqrt_u32(
	input			clk,
	input			rst_n,
	input			vld_in,
	input	[31:0]	x,
	output			vld_out,
	output	[15:0]	y
);

reg		[31:0]	x_reg	[15:0];
reg		[15:0]	valid_reg;
reg		[15:0]	q_reg	[15:0];
reg		[16:0]	s_reg	[15:0];
wire	[31:0]	x_o	[15:0];
wire	[15:0]	valid_o;
wire	[15:0]	q_o	[15:0];
wire	[16:0]	s_o	[15:0];
genvar i_gen;
generate 
	for(i_gen = 0; i_gen < 16; i_gen = i_gen + 1)begin
		if(i_gen == 0)begin
			always @(posedge clk)begin
				if(!rst_n)begin
					x_reg[0]		<= 0;
					valid_reg[0]	<= 0;
					q_reg[0]		<= 0;
					s_reg[0]		<= 0;
				end
				else begin
					x_reg[0]		<= x_o[0];
					valid_reg[0]	<= valid_o[0];
					q_reg[0]		<= q_o[0];
					s_reg[0]		<= s_o[0];
				end
			end 

			partial_cal pc_0(
				.x_i		(x),
				.valid_i	(vld_in),
				.q_i		(16'b0),
				.s_i		({15'b0,x[31:30]}),
				.x_o		(x_o[0]),
				.valid_o	(valid_o[0]),
				.q_o		(q_o[0]),
				.s_o		(s_o[0])	
			);
		
		end
		else begin
			always @(posedge clk)begin
				if(!rst_n)begin
					x_reg[i_gen]		<= 0;
					valid_reg[i_gen]	<= 0;
					q_reg[i_gen]		<= 0;
					s_reg[i_gen]		<= 0;
				end
				else begin
					x_reg[i_gen]		<= x_o[i_gen];
					valid_reg[i_gen]	<= valid_o[i_gen];
					q_reg[i_gen]		<= q_o[i_gen];
					s_reg[i_gen]		<= s_o[i_gen];
				end
			end 
			
			partial_cal pc_i(
				.x_i		(x_reg[i_gen - 1]),
				.valid_i	(valid_reg[i_gen - 1]),
				.q_i		(q_reg[i_gen - 1]),
				.s_i		(s_reg[i_gen - 1]),
				.x_o		(x_o[i_gen]),
				.valid_o	(valid_o[i_gen]),
				.q_o		(q_o[i_gen]),
				.s_o		(s_o[i_gen])	
			);
		end
	end
endgenerate
	
	assign vld_out  = valid_reg[15];
	assign y		= q_reg[15];

endmodule

sqrt_u32/src/sqrt_u32_tb.v
`timescale 1ps/1ps
module testbench ();
    
    reg clk,rst_n,vld_in;
    reg [31:0] x;
    wire vld_out;
    wire [15:0] y;
	
	initial begin
	$dumpfile("../sqrt_u32_tb.vcd");
	$dumpvars;
	end

    initial begin
        clk <= 1'b0;
        rst_n <= 1'b0;
        vld_in <= 1'b0;
        x <= 0;
        #4
        rst_n <= 1'b1;
        vld_in <= 1'b1;
        x <= 32'h0000_0076;
		#2
		x <= 256;
        #2
        x <= 255;
        #2
        x <= 2147483648;
        #2
        x <= 4294967295;
		#2
		vld_in <= 1'b0;
		#10
		vld_in <= 1'b1;
		x	<= 1369;
		#2
		x	<= 1368;
		#2
		vld_in <= 1'b0;
		#40
		$finish;
    end

    always #1 clk <= ~clk;

    sqrt_u32 dut(
        .clk(clk),
        .rst_n(rst_n),
        .vld_in(vld_in),
        .x(x),
        .vld_out(vld_out),
        .y(y)
    );

endmodule

sqrt_u32/sim/sqrt_u32_tb.vcd
$date
	Mon Dec 25 17:04:38 2023
$end
$version
	Icarus Verilog
$end
$timescale
	1ps
$end
$scope module testbench $end
$var wire 16 ! y [15:0] $end
$var wire 1 " vld_out $end
$var reg 1 # clk $end
$var reg 1 $ rst_n $end
$var reg 1 % vld_in $end
$var reg 32 & x [31:0] $end
$scope module dut $end
$var wire 1 # clk $end
$var wire 1 $ rst_n $end
$var wire 1 % vld_in $end
$var wire 32 ' x [31:0] $end
$var wire 16 ( y [15:0] $end
$var wire 1 " vld_out $end
$var wire 16 ) valid_o [15:0] $end
$var reg 16 * valid_reg [15:0] $end
$scope begin genblk1[0] $end
$scope begin genblk1 $end
$scope module pc_0 $end
$var wire 16 + q_i [15:0] $end
$var wire 17 , s_i [16:0] $end
$var wire 1 % valid_i $end
$var wire 1 - valid_o $end
$var wire 32 . x_i [31:0] $end
$var wire 32 / x_o [31:0] $end
$var wire 18 0 tmp [17:0] $end
$var wire 17 1 s_o [16:0] $end
$var wire 16 2 q_o [15:0] $end
$var wire 17 3 diff [16:0] $end
$upscope $end
$upscope $end
$upscope $end
$scope begin genblk1[1] $end
$scope begin genblk1 $end
$scope module pc_i $end
$var wire 16 4 q_i [15:0] $end
$var wire 17 5 s_i [16:0] $end
$var wire 1 6 valid_i $end
$var wire 1 7 valid_o $end
$var wire 32 8 x_i [31:0] $end
$var wire 32 9 x_o [31:0] $end
$var wire 18 : tmp [17:0] $end
$var wire 17 ; s_o [16:0] $end
$var wire 16 < q_o [15:0] $end
$var wire 17 = diff [16:0] $end
$upscope $end
$upscope $end
$upscope $end
$scope begin genblk1[2] $end
$scope begin genblk1 $end
$scope module pc_i $end
$var wire 16 > q_i [15:0] $end
$var wire 17 ? s_i [16:0] $end
$var wire 1 @ valid_i $end
$var wire 1 A valid_o $end
$var wire 32 B x_i [31:0] $end
$var wire 32 C x_o [31:0] $end
$var wire 18 D tmp [17:0] $end
$var wire 17 E s_o [16:0] $end
$var wire 16 F q_o [15:0] $end
$var wire 17 G diff [16:0] $end
$upscope $end
$upscope $end
$upscope $end
$scope begin genblk1[3] $end
$scope begin genblk1 $end
$scope module pc_i $end
$var wire 16 H q_i [15:0] $end
$var wire 17 I s_i [16:0] $end
$var wire 1 J valid_i $end
$var wire 1 K valid_o $end
$var wire 32 L x_i [31:0] $end
$var wire 32 M x_o [31:0] $end
$var wire 18 N tmp [17:0] $end
$var wire 17 O s_o [16:0] $end
$var wire 16 P q_o [15:0] $end
$var wire 17 Q diff [16:0] $end
$upscope $end
$upscope $end
$upscope $end
$scope begin genblk1[4] $end
$scope begin genblk1 $end
$scope module pc_i $end
$var wire 16 R q_i [15:0] $end
$var wire 17 S s_i [16:0] $end
$var wire 1 T valid_i $end
$var wire 1 U valid_o $end
$var wire 32 V x_i [31:0] $end
$var wire 32 W x_o [31:0] $end
$var wire 18 X tmp [17:0] $end
$var wire 17 Y s_o [16:0] $end
$var wire 16 Z q_o [15:0] $end
$var wire 17 [ diff [16:0] $end
$upscope $end
$upscope $end
$upscope $end
$scope begin genblk1[5] $end
$scope begin genblk1 $end
$scope module pc_i $end
$var wire 16 \ q_i [15:0] $end
$var wire 17 ] s_i [16:0] $end
$var wire 1 ^ valid_i $end
$var wire 1 _ valid_o $end
$var wire 32 ` x_i [31:0] $end
$var wire 32 a x_o [31:0] $end
$var wire 18 b tmp [17:0] $end
$var wire 17 c s_o [16:0] $end
$var wire 16 d q_o [15:0] $end
$var wire 17 e diff [16:0] $end
$upscope $end
$upscope $end
$upscope $end
$scope begin genblk1[6] $end
$scope begin genblk1 $end
$scope module pc_i $end
$var wire 16 f q_i [15:0] $end
$var wire 17 g s_i [16:0] $end
$var wire 1 h valid_i $end
$var wire 1 i valid_o $end
$var wire 32 j x_i [31:0] $end
$var wire 32 k x_o [31:0] $end
$var wire 18 l tmp [17:0] $end
$var wire 17 m s_o [16:0] $end
$var wire 16 n q_o [15:0] $end
$var wire 17 o diff [16:0] $end
$upscope $end
$upscope $end
$upscope $end
$scope begin genblk1[7] $end
$scope begin genblk1 $end
$scope module pc_i $end
$var wire 16 p q_i [15:0] $end
$var wire 17 q s_i [16:0] $end
$var wire 1 r valid_i $end
$var wire 1 s valid_o $end
$var wire 32 t x_i [31:0] $end
$var wire 32 u x_o [31:0] $end
$var wire 18 v tmp [17:0] $end
$var wire 17 w s_o [16:0] $end
$var wire 16 x q_o [15:0] $end
$var wire 17 y diff [16:0] $end
$upscope $end
$upscope $end
$upscope $end
$scope begin genblk1[8] $end
$scope begin genblk1 $end
$scope module pc_i $end
$var wire 16 z q_i [15:0] $end
$var wire 17 { s_i [16:0] $end
$var wire 1 | valid_i $end
$var wire 1 } valid_o $end
$var wire 32 ~ x_i [31:0] $end
$var wire 32 !" x_o [31:0] $end
$var wire 18 "" tmp [17:0] $end
$var wire 17 #" s_o [16:0] $end
$var wire 16 $" q_o [15:0] $end
$var wire 17 %" diff [16:0] $end
$upscope $end
$upscope $end
$upscope $end
$scope begin genblk1[9] $end
$scope begin genblk1 $end
$scope module pc_i $end
$var wire 16 &" q_i [15:0] $end
$var wire 17 '" s_i [16:0] $end
$var wire 1 (" valid_i $end
$var wire 1 )" valid_o $end
$var wire 32 *" x_i [31:0] $end
$var wire 32 +" x_o [31:0] $end
$var wire 18 ," tmp [17:0] $end
$var wire 17 -" s_o [16:0] $end
$var wire 16 ." q_o [15:0] $end
$var wire 17 /" diff [16:0] $end
$upscope $end
$upscope $end
$upscope $end
$scope begin genblk1[10] $end
$scope begin genblk1 $end
$scope module pc_i $end
$var wire 16 0" q_i [15:0] $end
$var wire 17 1" s_i [16:0] $end
$var wire 1 2" valid_i $end
$var wire 1 3" valid_o $end
$var wire 32 4" x_i [31:0] $end
$var wire 32 5" x_o [31:0] $end
$var wire 18 6" tmp [17:0] $end
$var wire 17 7" s_o [16:0] $end
$var wire 16 8" q_o [15:0] $end
$var wire 17 9" diff [16:0] $end
$upscope $end
$upscope $end
$upscope $end
$scope begin genblk1[11] $end
$scope begin genblk1 $end
$scope module pc_i $end
$var wire 16 :" q_i [15:0] $end
$var wire 17 ;" s_i [16:0] $end
$var wire 1 <" valid_i $end
$var wire 1 =" valid_o $end
$var wire 32 >" x_i [31:0] $end
$var wire 32 ?" x_o [31:0] $end
$var wire 18 @" tmp [17:0] $end
$var wire 17 A" s_o [16:0] $end
$var wire 16 B" q_o [15:0] $end
$var wire 17 C" diff [16:0] $end
$upscope $end
$upscope $end
$upscope $end
$scope begin genblk1[12] $end
$scope begin genblk1 $end
$scope module pc_i $end
$var wire 16 D" q_i [15:0] $end
$var wire 17 E" s_i [16:0] $end
$var wire 1 F" valid_i $end
$var wire 1 G" valid_o $end
$var wire 32 H" x_i [31:0] $end
$var wire 32 I" x_o [31:0] $end
$var wire 18 J" tmp [17:0] $end
$var wire 17 K" s_o [16:0] $end
$var wire 16 L" q_o [15:0] $end
$var wire 17 M" diff [16:0] $end
$upscope $end
$upscope $end
$upscope $end
$scope begin genblk1[13] $end
$scope begin genblk1 $end
$scope module pc_i $end
$var wire 16 N" q_i [15:0] $end
$var wire 17 O" s_i [16:0] $end
$var wire 1 P" valid_i $end
$var wire 1 Q" valid_o $end
$var wire 32 R" x_i [31:0] $end
$var wire 32 S" x_o [31:0] $end
$var wire 18 T" tmp [17:0] $end
$var wire 17 U" s_o [16:0] $end
$var wire 16 V" q_o [15:0] $end
$var wire 17 W" diff [16:0] $end
$upscope $end
$upscope $end
$upscope $end
$scope begin genblk1[14] $end
$scope begin genblk1 $end
$scope module pc_i $end
$var wire 16 X" q_i [15:0] $end
$var wire 17 Y" s_i [16:0] $end
$var wire 1 Z" valid_i $end
$var wire 1 [" valid_o $end
$var wire 32 \" x_i [31:0] $end
$var wire 32 ]" x_o [31:0] $end
$var wire 18 ^" tmp [17:0] $end
$var wire 17 _" s_o [16:0] $end
$var wire 16 `" q_o [15:0] $end
$var wire 17 a" diff [16:0] $end
$upscope $end
$upscope $end
$upscope $end
$scope begin genblk1[15] $end
$scope begin genblk1 $end
$scope module pc_i $end
$var wire 16 b" q_i [15:0] $end
$var wire 17 c" s_i [16:0] $end
$var wire 1 d" valid_i $end
$var wire 1 e" valid_o $end
$var wire 32 f" x_i [31:0] $end
$var wire 32 g" x_o [31:0] $end
$var wire 18 h" tmp [17:0] $end
$var wire 17 i" s_o [16:0] $end
$var wire 16 j" q_o [15:0] $end
$var wire 17 k" diff [16:0] $end
$upscope $end
$upscope $end
$upscope $end
$upscope $end
$upscope $end
$enddefinitions $end
#0
$dumpvars
bx k"
bx j"
bx i"
bx h"
bx00 g"
bx f"
xe"
xd"
bx c"
bx b"
bx a"
bx `"
bx _"
bx ^"
bx00 ]"
bx \"
x["
xZ"
bx Y"
bx X"
bx W"
bx V"
bx U"
bx T"
bx00 S"
bx R"
xQ"
xP"
bx O"
bx N"
bx M"
bx L"
bx K"
bx J"
bx00 I"
bx H"
xG"
xF"
bx E"
bx D"
bx C"
bx B"
bx A"
bx @"
bx00 ?"
bx >"
x="
x<"
bx ;"
bx :"
bx 9"
bx 8"
bx 7"
bx 6"
bx00 5"
bx 4"
x3"
x2"
bx 1"
bx 0"
bx /"
bx ."
bx -"
bx ,"
bx00 +"
bx *"
x)"
x("
bx '"
bx &"
bx %"
bx $"
bx #"
bx ""
bx00 !"
bx ~
x}
x|
bx {
bx z
bx y
bx x
bx w
bx v
bx00 u
bx t
xs
xr
bx q
bx p
bx o
bx n
bx m
bx l
bx00 k
bx j
xi
xh
bx g
bx f
bx e
bx d
bx c
bx b
bx00 a
bx `
x_
x^
bx ]
bx \
bx [
bx Z
bx Y
bx X
bx00 W
bx V
xU
xT
bx S
bx R
bx Q
bx P
bx O
bx N
bx00 M
bx L
xK
xJ
bx I
bx H
bx G
bx F
bx E
bx D
bx00 C
bx B
xA
x@
bx ?
bx >
bx =
bx <
bx ;
bx :
bx00 9
bx 8
x7
x6
bx 5
bx 4
b11111111111111111 3
b0 2
b0 1
b1 0
b0 /
b0 .
0-
b0 ,
b0 +
bx *
bx0 )
bx (
b0 '
b0 &
0%
0$
0#
x"
bx !
$end
#1
b11111111111111111 =
b0 <
b0 ;
b11111111111111111 G
b0 F
b0 E
b11111111111111111 Q
b0 P
b0 O
b11111111111111111 [
b0 Z
b0 Y
b11111111111111111 e
b0 d
b0 c
b11111111111111111 o
b0 n
b0 m
b11111111111111111 y
b0 x
b0 w
b11111111111111111 %"
b0 $"
b0 #"
b11111111111111111 /"
b0 ."
b0 -"
b11111111111111111 9"
b0 8"
b0 7"
b11111111111111111 C"
b0 B"
b0 A"
b11111111111111111 M"
b0 L"
b0 K"
b11111111111111111 W"
b0 V"
b0 U"
b11111111111111111 a"
b0 `"
b0 _"
b11111111111111111 k"
b0 j"
b0 i"
b1 :
07
06
b0 9
b1 D
0A
0@
b0 C
b1 N
0K
0J
b0 M
b1 X
0U
0T
b0 W
b1 b
0_
0^
b0 a
b1 l
0i
0h
b0 k
b1 v
0s
0r
b0 u
b1 ""
0}
0|
b0 !"
b1 ,"
0)"
0("
b0 +"
b1 6"
03"
02"
b0 5"
b1 @"
0="
0<"
b0 ?"
b1 J"
0G"
0F"
b0 I"
b1 T"
0Q"
0P"
b0 S"
b1 ^"
0["
0Z"
b0 ]"
b1 h"
b0 )
0e"
0d"
b0 g"
0"
b0 5
b0 4
b0 8
b0 ?
b0 >
b0 B
b0 I
b0 H
b0 L
b0 S
b0 R
b0 V
b0 ]
b0 \
b0 `
b0 g
b0 f
b0 j
b0 q
b0 p
b0 t
b0 {
b0 z
b0 ~
b0 '"
b0 &"
b0 *"
b0 1"
b0 0"
b0 4"
b0 ;"
b0 :"
b0 >"
b0 E"
b0 D"
b0 H"
b0 O"
b0 N"
b0 R"
b0 Y"
b0 X"
b0 \"
b0 c"
b0 b"
b0 f"
b0 !
b0 (
b0 *
1#
#2
0#
#3
1#
#4
b111011000 /
0#
b1110110 &
b1110110 '
b1110110 .
b1 )
1-
1%
1$
#5
b11 )
17
16
b11101100000 9
b1 *
b111011000 8
1#
#6
b10000000000 /
0#
b100000000 &
b100000000 '
b100000000 .
#7
b111 )
1A
1@
b1110110000000 C
b1000000000000 9
b11 *
b11101100000 B
b10000000000 8
1#
#8
b1111111100 /
0#
b11111111 &
b11111111 '
b11111111 .
#9
b111111110000 9
b100000000000000 C
b1111 )
1K
1J
b111011000000000 M
b1111111100 8
b1000000000000 B
b111 *
b1110110000000 L
1#
#10
b1 3
b1 2
b100 1
b10 ,
b0 /
0#
b10000000000000000000000000000000 &
b10000000000000000000000000000000 '
b10000000000000000000000000000000 .
#11
b11111 )
1U
1T
b11101100000000000 W
b10000000000000000 M
b11111111000000 C
b10 <
b10000 ;
b101 :
b0 9
b1111 *
b111011000000000 V
b100000000000000 L
b111111110000 B
b100 5
b1 4
b0 8
1#
#12
b10 3
b1011 1
b11 ,
b11111111111111111111111111111100 /
0#
b11111111111111111111111111111111 &
b11111111111111111111111111111111 '
b11111111111111111111111111111111 .
#13
b110 =
b11 <
b11011 ;
b11111111111111111111111111110000 9
b111 G
b101 F
b11100 E
b1001 D
b0 C
b1111111100000000 M
b1000000000000000000 W
b111111 )
1_
1^
b1110110000000000000 a
b1011 5
b11111111111111111111111111111100 8
b10000 ?
b10 >
b0 B
b11111111000000 L
b10000000000000000 V
b11111 *
b11101100000000000 `
1#
#14
0#
b111110 )
0-
0%
#15
b111 F
b111011 E
1i
1h
b111011000000000000000 k
b100000000000000000000 a
b111111110000000000 W
b111 Q
b1011 P
b11100 O
b10101 N
b0 M
b1110 G
b1101 D
b11111111111111111111111111000000 C
b1111100 )
07
06
b1110110000000000000 j
b1000000000000000000 `
b1111111100000000 V
b11100 I
b101 H
b0 L
b11011 ?
b11 >
b11111111111111111111111111110000 B
b111110 *
1#
#16
0#
#17
b1111 P
b1111011 O
0A
0@
b11110 Q
b11101 N
b11111111111111111111111100000000 M
b11111111111101111 [
b10110 Z
b1110000 Y
b101101 X
b0 W
b11111111000000000000 a
b10000000000000000000000 k
b11111000 )
1s
1r
b11101100000000000000000 u
b111011 I
b111 H
b11111111111111111111111111000000 L
b11100 S
b1011 R
b0 V
b111111110000000000 `
b100000000000000000000 j
b1111100 *
b111011000000000000000 t
1#
#18
0#
#19
1}
1|
b1110110000000000000000000 !"
b1000000000000000000000000 u
b1111111100000000000000 k
b10111 e
b101101 d
b1011100 c
b1011001 b
b0 a
b111110 [
b11111 Z
b11111011 Y
b111101 X
b11111111111111111111110000000000 W
b111110000 )
0K
0J
b11101100000000000000000 ~
b10000000000000000000000 t
b11111111000000000000 j
b1110000 ]
b10110 \
b0 `
b1111011 S
b1111 R
b11111111111111111111111100000000 V
b11111000 *
1#
#20
0#
#21
b111111 d
b111111011 c
0U
0T
b1111110 e
b1111101 b
b11111111111111111111000000000000 a
b11111111110100111 o
b1011010 n
b101110000 m
b10110101 l
b0 k
b111111110000000000000000 u
b100000000000000000000000000 !"
b1111100000 )
1)"
1("
b111011000000000000000000000 +"
b11111011 ]
b11111 \
b11111111111111111111110000000000 `
b1011100 g
b101101 f
b0 j
b1111111100000000000000 t
b1000000000000000000000000 ~
b111110000 *
b1110110000000000000000000 *"
1#
#22
0#
#23
13"
12"
b11101100000000000000000000000 5"
b10000000000000000000000000000 +"
b11111111000000000000000000 !"
b111 y
b10110101 x
b11100 w
b101101001 v
b0 u
b11111110 o
b1111111 n
b1111111011 m
b11111101 l
b11111111111111111100000000000000 k
b11111000000 )
0_
0^
b111011000000000000000000000 4"
b100000000000000000000000000 *"
b111111110000000000000000 ~
b101110000 q
b1011010 p
b0 t
b111111011 g
b111111 f
b11111111111111111111000000000000 j
b1111100000 *
1#
#24
b11111111111111111 3
b0 2
b0 1
b0 ,
b1010101100100 /
0#
b10101011001 &
b10101011001 '
b10101011001 .
b11111000001 )
1-
1%
#25
b11111111 x
b11111111011 w
b1 7"
b1 A"
b11111111111111111 =
b0 <
b0 ;
b1 :
17
16
b101010110010000 9
0i
0h
b111111110 y
b111111101 v
b11111111111111110000000000000000 u
b11111110101000111 %"
b101101010 $"
b1110000 #"
b1011010101 ""
b0 !"
b1111111100000000000000000000 +"
b1000000000000000000000000000000 5"
b111110000011 )
1="
1<"
b1110110000000000000000000000000 ?"
b0 5
b0 4
b1010101100100 8
b1111111011 q
b1111111 p
b11111111111111111100000000000000 t
b11100 {
b10110101 z
b0 ~
b11111111000000000000000000 *"
b10000000000000000000000000000 4"
b11111000001 *
b11101100000000000000000000000 >"
1#
#26
b1010101100000 /
0#
b10101011000 &
b10101011000 '
b10101011000 .
#27
b0 7"
b0 M"
b1 L"
b11 K"
1G"
1F"
b11011000000000000000000000000000 I"
b0 C"
b1 B"
b0 A"
b0 ?"
b111111110000000000000000000000 5"
b11111101011000111 /"
b1011010100 ."
b111000000 -"
b10110101001 ,"
b0 +"
b1111111110 %"
b111111111 $"
b111111111011 #"
b1111111101 ""
b11111111111111000000000000000000 !"
0s
0r
b11111111111111111 G
b0 F
b0 E
b1 D
b1111100000111 )
1A
1@
b10101011001000000 C
b101010110000000 9
b1 E"
b1110110000000000000000000000000 H"
b1 ;"
b1000000000000000000000000000000 >"
b1111111100000000000000000000 4"
b1110000 '"
b101101010 &"
b0 *"
b11111111011 {
b11111111 z
b11111111111111110000000000000000 ~
b0 ?
b0 >
b111110000011 *
b101010110010000 B
b1010101100000 8
1#
#28
0#
b1111100000110 )
0-
0%
#29
07
06
b10101011000000000 C
b11111111111111111 Q
b0 P
b0 O
b1 N
1K
1J
b1010101100100000000 M
0}
0|
b11111111110 /"
b1111111111 ."
b1111111111011 -"
b11111111101 ,"
b11111111111100000000000000000000 +"
b11111011001101111 9"
b10110101000 8"
b11100000000 7"
b101101010001 6"
b0 5"
b11111111111111111 C"
b0 B"
b11 A"
b11111111000000000000000000000000 ?"
b11111111111111011 M"
b10 L"
b0 K"
b101 J"
b0 I"
b11111111111111110 W"
b10 V"
b1101 U"
b101 T"
b11111000001100 )
1Q"
1P"
b1100000000000000000000000000000 S"
b101010110000000 B
b0 I
b0 H
b10101011001000000 L
b111111111011 '"
b111111111 &"
b11111111111111000000000000000000 *"
b111000000 1"
b1011010100 0"
b0 4"
b0 ;"
b111111110000000000000000000000 >"
b0 E"
b1 D"
b0 H"
b11 O"
b1 N"
b1111100000110 *
b11011000000000000000000000000000 R"
1#
#30
0#
#31
b100 V"
b0 U"
b1 L"
b1011 K"
b100 a"
b101 `"
b10010 _"
b1001 ^"
1["
1Z"
b10000000000000000000000000000000 ]"
b11111111111110111 W"
b1001 T"
b0 S"
b10 M"
b1 J"
b11111100000000000000000000000000 I"
b11111000001011111 C"
b101101010000 B"
b1110000000000 A"
b1011010100001 @"
b0 ?"
b111111111110 9"
b11111111111 8"
b11111111111011 7"
b111111111101 6"
b11111111110000000000000000000000 5"
0)"
0("
b11111111111111111 [
b0 Z
b0 Y
b1 X
1U
1T
b101010110010000000000 W
b1010101100000000000 M
b111110000011000 )
0A
0@
b1101 Y"
b10 X"
b1100000000000000000000000000000 \"
b0 O"
b10 N"
b0 R"
b11 E"
b0 D"
b11111111000000000000000000000000 H"
b11100000000 ;"
b10110101000 :"
b0 >"
b1111111111011 1"
b1111111111 0"
b11111111111100000000000000000000 4"
b0 S
b0 R
b1010101100100000000 V
b10101011000000000 L
b11111000001100 *
1#
#32
0#
#33
b1011010100000 L"
b111000000000000 K"
0K
0J
b101010110000000000000 W
b11111111111111111 e
b0 d
b0 c
b1 b
1_
1^
b10101011001000000000000 a
03"
02"
b1111111111110 C"
b111111111111 B"
b111111111111011 A"
b1111111111101 @"
b11111111000000000000000000000000 ?"
b11110111010111111 M"
b10110101000001 J"
b0 I"
b110 W"
b11 V"
b11011 U"
b101 T"
b11110000000000000000000000000000 S"
b11111111111101111 a"
b1000 `"
b0 _"
b10001 ^"
b0 ]"
b11111111111111101 k"
b1010 j"
b1001000 i"
b10101 h"
b1111100000110000 )
1e"
1d"
b1010101100000000000 V
b0 ]
b0 \
b101010110010000000000 `
b11111111111011 ;"
b11111111111 :"
b11111111110000000000000000000000 >"
b1110000000000 E"
b101101010000 D"
b0 H"
b1011 O"
b1 N"
b11111100000000000000000000000000 R"
b0 Y"
b100 X"
b0 \"
b10010 c"
b101 b"
b111110000011000 *
b10000000000000000000000000000000 f"
1#
#34
0#
#35
b0 i"
b10000 j"
b10110101000001 V"
b101010111111100 U"
1"
b11111111111011111 k"
b100001 h"
b1110 a"
b111 `"
b111011 _"
b1101 ^"
b11000000000000000000000000000000 ]"
b1010101111111 W"
b101101010000001 T"
b0 S"
b11111111111110 M"
b1111111111111 L"
b1111111111111011 K"
b11111111111101 J"
b11111100000000000000000000000000 I"
0="
0<"
b11111111111111111 o
b0 n
b0 m
b1 l
1i
1h
b1010101100100000000000000 k
b10101011000000000000000 a
b1111000001100000 )
0U
0T
b1010 !
b1010 (
b0 c"
b1000 b"
b0 f"
b11011 Y"
b11 X"
b11110000000000000000000000000000 \"
b111000000000000 O"
b1011010100000 N"
b0 R"
b111111111111011 E"
b111111111111 D"
b11111111000000000000000000000000 H"
b0 g
b0 f
b10101011001000000000000 j
b101010110000000000000 `
b1111100000110000 *
1#
#36
0#
#37
b11111111111111 V"
b11111111111111011 U"
b101101010000010 `"
b10101011111110000 _"
0_
0^
b1010101100000000000000000 k
b11111111111111111 y
b0 x
b0 w
b1 v
1s
1r
b101010110010000000000000000 u
b1110000011000000 )
0G"
0F"
b111111111111110 W"
b111111111111101 T"
b11110000000000000000000000000000 S"
b11010000011110111 a"
b1011010100000101 ^"
b0 ]"
b11110 k"
b1111 j"
b1111000 i"
b11101 h"
b10101011000000000000000 j
b0 q
b0 p
b1010101100100000000000000 t
b1111000001100000 *
b1111111111111011 O"
b1111111111111 N"
b11111100000000000000000000000000 R"
b101010111111100 Y"
b10110101000001 X"
b0 \"
b111011 c"
b111 b"
b11000000000000000000000000000000 f"
b10000 !
b10000 (
1#
#38
0#
#39
b10101111111000000 i"
b1011010100000100 j"
b11110110111100111 k"
b10110101000001001 h"
b1111111111111110 a"
b111111111111111 `"
b11111111111111011 _"
b1111111111111101 ^"
b11000000000000000000000000000000 ]"
0Q"
0P"
b11111111111111111 %"
b0 $"
b0 #"
b1 ""
1}
1|
b10101011001000000000000000000 !"
b101010110000000000000000000 u
b1100000110000000 )
0i
0h
b1111 !
b1111 (
b10101011111110000 c"
b101101010000010 b"
b0 f"
b11111111111111011 Y"
b11111111111111 X"
b11110000000000000000000000000000 \"
b0 {
b0 z
b101010110010000000000000000 ~
b1010101100000000000000000 t
b1110000011000000 *
1#
#40
0#
#41
0s
0r
b10101011000000000000000000000 !"
b11111111111111111 /"
b0 ."
b1 -"
b1 ,"
1)"
1("
b1010101100100000000000000000000 +"
b1000001100000000 )
0["
0Z"
b11111111111111110 k"
b1111111111111110 j"
b11111111111101100 i"
b11111111111111101 h"
b101010110000000000000000000 ~
b0 '"
b0 &"
b10101011001000000000000000000 *"
b1100000110000000 *
b11111111111111011 c"
b111111111111111 b"
b11000000000000000000000000000000 f"
b1011010100000100 !
b1011010100000100 (
1#
#42
0#
#43
0e"
0d"
b0 9"
b1 8"
b1 7"
b1 6"
13"
12"
b1010110010000000000000000000000 5"
b1010101100000000000000000000000 +"
b11000000000 )
0}
0|
b1111111111111110 !
b1111111111111110 (
b1 1"
b0 0"
b1010101100100000000000000000000 4"
b10101011000000000000000000000 *"
b1000001100000000 *
1#
#44
0#
#45
0)"
0("
b1010110000000000000000000000000 5"
b11111111111111100 C"
b10 B"
b101 A"
b101 @"
b110000000000 )
1="
1<"
b1011001000000000000000000000000 ?"
0"
b1010101100000000000000000000000 4"
b1 ;"
b1 :"
b1010110010000000000000000000000 >"
b11000000000 *
1#
#46
0#
#47
b11111111111111100 M"
b100 L"
b10101 K"
b1001 J"
1G"
1F"
b1100100000000000000000000000000 I"
b1011000000000000000000000000000 ?"
b1100000000000 )
03"
02"
b101 E"
b10 D"
b1011001000000000000000000000000 H"
b1010110000000000000000000000000 >"
b110000000000 *
1#
#48
0#
#49
0="
0<"
b1100000000000000000000000000000 I"
b100 W"
b1001 V"
b10010 U"
b10001 T"
b11000000000000 )
1Q"
1P"
b10010000000000000000000000000000 S"
b1011000000000000000000000000000 H"
b10101 O"
b100 N"
b1100000000000 *
b1100100000000000000000000000000 R"
1#
#50
0#
#51
b11111111111101101 a"
b10010 `"
b1001001 _"
b100101 ^"
1["
1Z"
b1000000000000000000000000000000 ]"
b10000000000000000000000000000000 S"
b110000000000000 )
0G"
0F"
b10010 Y"
b1001 X"
b10010000000000000000000000000000 \"
b1100000000000000000000000000000 R"
b11000000000000 *
1#
#52
0#
#53
b1001000 _"
b0 i"
b100101 j"
0Q"
0P"
b0 ]"
b0 k"
b1001001 h"
b1100000000000000 )
1e"
1d"
b10000000000000000000000000000000 \"
b1001001 c"
b10010 b"
b110000000000000 *
b1000000000000000000000000000000 f"
1#
#54
0#
#55
1"
b11111111111111111 k"
b100100 j"
b100100000 i"
b1000000000000000 )
0["
0Z"
b100101 !
b100101 (
b1001000 c"
b0 f"
b1100000000000000 *
1#
#56
0#
#57
b0 )
0e"
0d"
b1000000000000000 *
b100100 !
b100100 (
1#
#58
0#
#59
0"
b0 *
1#
